[{"ADHERENCE": "30", "BLOCKID": "222", "BLOCK_ABBR": "193-4", "DIRECTION": "Southbound", "LATITUDE": "33.5857122", "LONGITUDE": "-84.5156242", "MSGTIME": "4/16/2018 6:31:12 PM", "ROUTE": "193", "STOPID": "176106", "TIMEPOINT": "Old Natl Hwy & Godby Rd", "TRIPID": "6171836", "VEHICLE": "1827"}, {"ADHERENCE": "-35", "BLOCKID": "36", "BLOCK_ABBR": "115-17", "DIRECTION": "Eastbound", "LATITUDE": "33.7559167", "LONGITUDE": "-84.2376297", "MSGTIME": "4/16/2018 6:31:39 PM", "ROUTE": "115", "STOPID": "134088", "TIMEPOINT": "Mall at Stonecrest", "TRIPID": "6145792", "VEHICLE": "1627"}, {"ADHERENCE": "0", "BLOCKID": "32", "BLOCK_ABBR": "115-13", "DIRECTION": "Eastbound", "LATITUDE": "33.7696162", "LONGITUDE": "-84.2291349", "MSGTIME": "4/16/2018 6:32:57 PM", "ROUTE": "115", "STOPID": "134088", "TIMEPOINT": "Mall at Stonecrest", "TRIPID": "6142278", "VEHICLE": "2492"}, {"ADHERENCE": "-9", "BLOCKID": "309", "BLOCK_ABBR": "30-6", "DIRECTION": "Northbound", "LATITUDE": "33.7923941", "LONGITUDE": "-84.2816943", "MSGTIME": "4/16/2018 6:33:03 PM", "ROUTE": "33", "STOPID": "905514", "TIMEPOINT": "Chamblee Station (East Loop)", "TRIPID": "6156016", "VEHICLE": "1624"}, {"ADHERENCE": "-4", "BLOCKID": "537", "BLOCK_ABBR": "86-3", "DIRECTION": "Westbound", "LATITUDE": "33.7032992", "LONGITUDE": "-84.1037076", "MSGTIME": "4/16/2018 6:33:07 PM", "ROUTE": "86", "STOPID": "134088", "TIMEPOINT": "Mall at Stonecrest", "TRIPID": "6154569", "VEHICLE": "1529"}, {"ADHERENCE": "-18", "BLOCKID": "321", "BLOCK_ABBR": "34-2", "DIRECTION": "Southbound", "LATITUDE": "33.6894686", "LONGITUDE": "-84.2727547", "MSGTIME": "4/16/2018 6:33:25 PM", "ROUTE": "34", "STOPID": "211422", "TIMEPOINT": "Clifton Church Rd & Gresham Rd", "TRIPID": "6172260", "VEHICLE": "1542"}, {"ADHERENCE": "-49", "BLOCKID": "243", "BLOCK_ABBR": "2-5", "DIRECTION": "Eastbound", "LATITUDE": "33.7624605", "LONGITUDE": "-84.3405116", "MSGTIME": "4/16/2018 6:33:42 PM", "ROUTE": "102", "STOPID": "904322", "TIMEPOINT": "Edgewood-Candler Park Station", "TRIPID": "6173773", "VEHICLE": "2566"}, {"ADHERENCE": "-4", "BLOCKID": "156", "BLOCK_ABBR": "15-4", "DIRECTION": "Southbound", "LATITUDE": "33.6537048", "LONGITUDE": "-84.236178", "MSGTIME": "4/16/2018 6:33:43 PM", "ROUTE": "15", "STOPID": "153090", "TIMEPOINT": "Panthersville Rd & Clifton Sp Rd", "TRIPID": "6151291", "VEHICLE": "1622"}, {"ADHERENCE": "-21", "BLOCKID": "137", "BLOCK_ABBR": "142-5", "DIRECTION": "Eastbound", "LATITUDE": "33.9666936", "LONGITUDE": "-84.2619384", "MSGTIME": "4/16/2018 6:33:53 PM", "ROUTE": "142", "STOPID": "213303", "TIMEPOINT": "Holcomb Bridge Rd & Nesbit Ferry", "TRIPID": "6171375", "VEHICLE": "1408"}, {"ADHERENCE": "0", "BLOCKID": "506", "BLOCK_ABBR": "84-8", "DIRECTION": "Westbound", "LATITUDE": "33.6635428", "LONGITUDE": "-84.3861706", "MSGTIME": "4/16/2018 6:34:45 PM", "ROUTE": "84", "STOPID": "190060", "TIMEPOINT": "Smith St & Broad St", "TRIPID": "6149816", "VEHICLE": "2373"}, {"ADHERENCE": "0", "BLOCKID": "447", "BLOCK_ABBR": "78-1", "DIRECTION": "Westbound", "LATITUDE": "33.6633789", "LONGITUDE": "-84.3856137", "MSGTIME": "4/16/2018 6:34:53 PM", "ROUTE": "78", "STOPID": "146900", "TIMEPOINT": "East Point Station", "TRIPID": "0", "VEHICLE": "2356"}, {"ADHERENCE": "0", "BLOCKID": "268", "BLOCK_ABBR": "221-4", "DIRECTION": "Eastbound", "LATITUDE": "33.8072177", "LONGITUDE": "-84.2415314", "MSGTIME": "4/16/2018 6:35:23 PM", "ROUTE": "221", "STOPID": "211482", "TIMEPOINT": "Memorial Drive Park & Ride", "TRIPID": "0", "VEHICLE": "2596"}, {"ADHERENCE": "-16", "BLOCKID": "45", "BLOCK_ABBR": "117-1", "DIRECTION": "Northbound", "LATITUDE": "33.775917", "LONGITUDE": "-84.2818516", "MSGTIME": "4/16/2018 6:37:05 PM", "ROUTE": "117", "STOPID": "903587", "TIMEPOINT": "North Decatur Rd & Church St", "TRIPID": "6152823", "VEHICLE": "1530"}, {"ADHERENCE": "-1", "BLOCKID": "173", "BLOCK_ABBR": "16-6", "DIRECTION": "Northbound", "LATITUDE": "33.8102406", "LONGITUDE": "-84.2730313", "MSGTIME": "4/16/2018 6:37:45 PM", "ROUTE": "16", "STOPID": "905666", "TIMEPOINT": "Lenox Station", "TRIPID": "0", "VEHICLE": "1636"}, {"ADHERENCE": "-4", "BLOCKID": "346", "BLOCK_ABBR": "40-4", "DIRECTION": "Southbound", "LATITUDE": "33.737251", "LONGITUDE": "-84.4177119", "MSGTIME": "4/16/2018 6:38:31 PM", "ROUTE": "40", "STOPID": "901264", "TIMEPOINT": "Peachtree St & Alabama St", "TRIPID": "6175617", "VEHICLE": "1485"}, {"ADHERENCE": "0", "BLOCKID": "508", "BLOCK_ABBR": "85-1", "DIRECTION": "Southbound", "LATITUDE": "33.9446537", "LONGITUDE": "-84.3572975", "MSGTIME": "4/16/2018 6:38:59 PM", "ROUTE": "185", "STOPID": "210484", "TIMEPOINT": "Alpharetta Hwy & Commerce Pkwy", "TRIPID": "6157943", "VEHICLE": "1560"}, {"ADHERENCE": "-4", "BLOCKID": "560", "BLOCK_ABBR": "89-5", "DIRECTION": "Northbound", "LATITUDE": "33.6642682", "LONGITUDE": "-84.3856068", "MSGTIME": "4/16/2018 6:39:46 PM", "ROUTE": "89", "STOPID": "900069", "TIMEPOINT": "Lancaster Ln & Shannon Pkwy", "TRIPID": "6142076", "VEHICLE": "2370"}, {"ADHERENCE": "0", "BLOCKID": "231", "BLOCK_ABBR": "196-2", "DIRECTION": "Southbound", "LATITUDE": "33.7012639", "LONGITUDE": "-84.4286825", "MSGTIME": "4/16/2018 6:39:53 PM", "ROUTE": "196", "STOPID": "212439", "TIMEPOINT": "ATL International Terminal", "TRIPID": "6165858", "VEHICLE": "1831"}, {"ADHERENCE": "-1", "BLOCKID": "205", "BLOCK_ABBR": "19-2", "DIRECTION": "Northbound", "LATITUDE": "33.8877389", "LONGITUDE": "-84.3051412", "MSGTIME": "4/16/2018 6:40:21 PM", "ROUTE": "19", "STOPID": "905514", "TIMEPOINT": "Chamblee Station (East Loop)", "TRIPID": "6155718", "VEHICLE": "2491"}, {"ADHERENCE": "-26", "BLOCKID": "532", "BLOCK_ABBR": "86-13", "DIRECTION": "Eastbound", "LATITUDE": "33.7547617", "LONGITUDE": "-84.2319957", "MSGTIME": "4/16/2018 6:40:34 PM", "ROUTE": "86", "STOPID": "134088", "TIMEPOINT": "Mall at Stonecrest", "TRIPID": "6165747", "VEHICLE": "1547"}, {"ADHERENCE": "0", "BLOCKID": "242", "BLOCK_ABBR": "2-4", "DIRECTION": "Northbound", "LATITUDE": "33.5173806", "LONGITUDE": "-84.6698124", "MSGTIME": "4/16/2018 6:40:56 PM", "ROUTE": "25", "STOPID": "190064", "TIMEPOINT": "Roosevelt Hwy & B Engram Pkwy", "TRIPID": "6149101", "VEHICLE": "1839"}, {"ADHERENCE": "0", "BLOCKID": "576", "BLOCK_ABBR": "95-3", "DIRECTION": "Southbound", "LATITUDE": "33.6620061", "LONGITUDE": "-84.3540059", "MSGTIME": "4/16/2018 6:41:40 PM", "ROUTE": "95", "STOPID": "148092", "TIMEPOINT": "King Arnold St & Sunset Dr", "TRIPID": "6160928", "VEHICLE": "2399"}, {"ADHERENCE": "-6", "BLOCKID": "64", "BLOCK_ABBR": "119-4", "DIRECTION": "Eastbound", "LATITUDE": "33.8109043", "LONGITUDE": "-84.1833403", "MSGTIME": "4/16/2018 6:41:57 PM", "ROUTE": "119", "STOPID": "210074", "TIMEPOINT": "Rockbridge Rd & Hairston Rd", "TRIPID": "6169394", "VEHICLE": "1648"}, {"ADHERENCE": "-17", "BLOCKID": "323", "BLOCK_ABBR": "34-4", "DIRECTION": "Southbound", "LATITUDE": "33.6895998", "LONGITUDE": "-84.2727381", "MSGTIME": "4/16/2018 6:42:01 PM", "ROUTE": "114", "STOPID": "153008", "TIMEPOINT": "Clifton Springs Health Center", "TRIPID": "6142170", "VEHICLE": "2552"}, {"ADHERENCE": "-11", "BLOCKID": "312", "BLOCK_ABBR": "30-9", "DIRECTION": "Southbound", "LATITUDE": "33.8210326", "LONGITUDE": "-84.3692638", "MSGTIME": "4/16/2018 6:42:15 PM", "ROUTE": "33", "STOPID": "901782", "TIMEPOINT": "Druid Hills Rd & Briarcliff Rd", "TRIPID": "6149224", "VEHICLE": "1605"}, {"ADHERENCE": "-12", "BLOCKID": "575", "BLOCK_ABBR": "95-2", "DIRECTION": "Northbound", "LATITUDE": "33.7365245", "LONGITUDE": "-84.4134738", "MSGTIME": "4/16/2018 6:42:36 PM", "ROUTE": "95", "STOPID": "137056", "TIMEPOINT": "Metropolitan Pky @ Atlanta Tech", "TRIPID": "6156986", "VEHICLE": "2407"}, {"ADHERENCE": "3", "BLOCKID": "368", "BLOCK_ABBR": "5-5", "DIRECTION": "Northbound", "LATITUDE": "33.9188685", "LONGITUDE": "-84.3516801", "MSGTIME": "4/16/2018 6:42:58 PM", "ROUTE": "5", "STOPID": "906308", "TIMEPOINT": "Roswell Rd & Hammond Dr", "TRIPID": "6175572", "VEHICLE": "1685"}, {"ADHERENCE": "0", "BLOCKID": "8", "BLOCK_ABBR": "103-3", "DIRECTION": "Southbound", "LATITUDE": "33.8883331", "LONGITUDE": "-84.3056947", "MSGTIME": "4/16/2018 6:43:06 PM", "ROUTE": "103", "STOPID": "905515", "TIMEPOINT": "Chamblee Station (West Loop)", "TRIPID": "6147669", "VEHICLE": "1402"}, {"ADHERENCE": "0", "BLOCKID": "75", "BLOCK_ABBR": "12-8", "DIRECTION": "Northbound", "LATITUDE": "33.8444829", "LONGITUDE": "-84.4251993", "MSGTIME": "4/16/2018 6:43:41 PM", "ROUTE": "12", "STOPID": "213236", "TIMEPOINT": "Northside Branch Library", "TRIPID": "6178292", "VEHICLE": "1448"}, {"ADHERENCE": "-3", "BLOCKID": "162", "BLOCK_ABBR": "150-1", "DIRECTION": "Eastbound", "LATITUDE": "33.9018721", "LONGITUDE": "-84.4423245", "MSGTIME": "4/16/2018 6:44:02 PM", "ROUTE": "150", "STOPID": "902866", "TIMEPOINT": "Chamblee-Dunwoody & Dunwoody Vi", "TRIPID": "0", "VEHICLE": "1487"}, {"ADHERENCE": "6", "BLOCKID": "33", "BLOCK_ABBR": "115-14", "DIRECTION": "Eastbound", "LATITUDE": "33.7549935", "LONGITUDE": "-84.2359857", "MSGTIME": "4/16/2018 6:44:03 PM", "ROUTE": "115", "STOPID": "134088", "TIMEPOINT": "Mall at Stonecrest", "TRIPID": "0", "VEHICLE": "1602"}, {"ADHERENCE": "0", "BLOCKID": "92", "BLOCK_ABBR": "121-4", "DIRECTION": "Northbound", "LATITUDE": "33.8340012", "LONGITUDE": "-84.2161007", "MSGTIME": "4/16/2018 6:44:15 PM", "ROUTE": "121", "STOPID": "901618", "TIMEPOINT": "Ponce de Leon Ave & Hairston Rd", "TRIPID": "6142318", "VEHICLE": "1550"}, {"ADHERENCE": "0", "BLOCKID": "524", "BLOCK_ABBR": "856-1", "DIRECTION": "Eastbound", "LATITUDE": "33.754262", "LONGITUDE": "-84.4688489", "MSGTIME": "4/16/2018 6:44:21 PM", "ROUTE": "856", "STOPID": "903320", "TIMEPOINT": "Hamilton E Holmes Station", "TRIPID": "6164929", "VEHICLE": "1664"}, {"ADHERENCE": "-9", "BLOCKID": "482", "BLOCK_ABBR": "82-8", "DIRECTION": "Westbound", "LATITUDE": "33.656343", "LONGITUDE": "-84.5030792", "MSGTIME": "4/16/2018 6:44:36 PM", "ROUTE": "82", "STOPID": "165038", "TIMEPOINT": "Washington Rd & Lakemont Dr", "TRIPID": "6173491", "VEHICLE": "2337"}, {"ADHERENCE": "0", "BLOCKID": "90", "BLOCK_ABBR": "121-2", "DIRECTION": "Northbound", "LATITUDE": "33.8491674", "LONGITUDE": "-84.1951476", "MSGTIME": "4/16/2018 6:44:41 PM", "ROUTE": "121", "STOPID": "213255", "TIMEPOINT": "Hugh Howell Rd & Flinstone Dr", "TRIPID": "6142311", "VEHICLE": "1401"}, {"ADHERENCE": "-6", "BLOCKID": "5", "BLOCK_ABBR": "1-5", "DIRECTION": "Southbound", "LATITUDE": "33.7838124", "LONGITUDE": "-84.4182001", "MSGTIME": "4/16/2018 6:45:02 PM", "ROUTE": "1", "STOPID": "900349", "TIMEPOINT": "Marietta Blvd @ Moores Mill Ctr", "TRIPID": "6173236", "VEHICLE": "2532"}, {"ADHERENCE": "-11", "BLOCKID": "240", "BLOCK_ABBR": "2-2", "DIRECTION": "Eastbound", "LATITUDE": "33.7614097", "LONGITUDE": "-84.3393353", "MSGTIME": "4/16/2018 6:45:18 PM", "ROUTE": "102", "STOPID": "213054", "TIMEPOINT": "Ponce de Leon Ave & Highland Ave", "TRIPID": "6145725", "VEHICLE": "1412"}, {"ADHERENCE": "0", "BLOCKID": "140", "BLOCK_ABBR": "143-10", "DIRECTION": "Southbound", "LATITUDE": "34.0148731", "LONGITUDE": "-84.3295028", "MSGTIME": "4/16/2018 6:45:50 PM", "ROUTE": "143", "STOPID": "902650", "TIMEPOINT": "Morris Rd @ One Verizon Place", "TRIPID": "6153482", "VEHICLE": "2546"}, {"ADHERENCE": "16", "BLOCKID": "555", "BLOCK_ABBR": "89-11", "DIRECTION": "Southbound", "LATITUDE": "33.6430974", "LONGITUDE": "-84.398959", "MSGTIME": "4/16/2018 6:46:03 PM", "ROUTE": "89", "STOPID": "900069", "TIMEPOINT": "Lancaster Ln & Shannon Pkwy", "TRIPID": "0", "VEHICLE": "2330"}, {"ADHERENCE": "4", "BLOCKID": "348", "BLOCK_ABBR": "40-6", "DIRECTION": "Southbound", "LATITUDE": "33.7531442", "LONGITUDE": "-84.4447446", "MSGTIME": "4/16/2018 6:46:16 PM", "ROUTE": "40", "STOPID": "902084", "TIMEPOINT": "Hollywood Rd & Arno Dr", "TRIPID": "6176186", "VEHICLE": "2535"}, {"ADHERENCE": "0", "BLOCKID": "288", "BLOCK_ABBR": "27-6", "DIRECTION": "Southbound", "LATITUDE": "33.7818723", "LONGITUDE": "-84.3864795", "MSGTIME": "4/16/2018 6:46:43 PM", "ROUTE": "27", "STOPID": "904800", "TIMEPOINT": "Midtown Station", "TRIPID": "6145589", "VEHICLE": "1683"}, {"ADHERENCE": "-3", "BLOCKID": "128", "BLOCK_ABBR": "141-2", "DIRECTION": "Southbound", "LATITUDE": "34.0445334", "LONGITUDE": "-84.2968734", "MSGTIME": "4/16/2018 6:46:44 PM", "ROUTE": "141", "STOPID": "212005", "TIMEPOINT": "Haynes Bridge Rd & Old Milton Py", "TRIPID": "6153224", "VEHICLE": "1458"}, {"ADHERENCE": "0", "BLOCKID": "184", "BLOCK_ABBR": "180-2", "DIRECTION": "Southbound", "LATITUDE": "33.6640533", "LONGITUDE": "-84.3850575", "MSGTIME": "4/16/2018 6:46:44 PM", "ROUTE": "178", "STOPID": "159282", "TIMEPOINT": "Cleveland Ave & Browns Mill Rd", "TRIPID": "6157931", "VEHICLE": "1835"}, {"ADHERENCE": "7", "BLOCKID": "499", "BLOCK_ABBR": "84-16", "DIRECTION": "Westbound", "LATITUDE": "33.5718587", "LONGITUDE": "-84.5645845", "MSGTIME": "4/16/2018 6:46:51 PM", "ROUTE": "84", "STOPID": "183036", "TIMEPOINT": "Buffington Rd & Flat Shoals Rd", "TRIPID": "6161825", "VEHICLE": "2366"}, {"ADHERENCE": "2", "BLOCKID": "475", "BLOCK_ABBR": "82-1", "DIRECTION": "Westbound", "LATITUDE": "33.618828", "LONGITUDE": "-84.5590085", "MSGTIME": "4/16/2018 6:47:22 PM", "ROUTE": "82", "STOPID": "210108", "TIMEPOINT": "Welcome All Rd & Jailette Rd", "TRIPID": "6177454", "VEHICLE": "2360"}, {"ADHERENCE": "-2", "BLOCKID": "358", "BLOCK_ABBR": "49-3", "DIRECTION": "Northbound", "LATITUDE": "33.753311", "LONGITUDE": "-84.391459", "MSGTIME": "4/16/2018 6:47:40 PM", "ROUTE": "49", "STOPID": "102248", "TIMEPOINT": "Alabama St & Peachtree St", "TRIPID": "6154973", "VEHICLE": "2367"}, {"ADHERENCE": "-3", "BLOCKID": "469", "BLOCK_ABBR": "81-6", "DIRECTION": "Northbound", "LATITUDE": "33.6854562", "LONGITUDE": "-84.4715866", "MSGTIME": "4/16/2018 6:47:43 PM", "ROUTE": "81", "STOPID": "146900", "TIMEPOINT": "East Point Station", "TRIPID": "6142020", "VEHICLE": "2316"}, {"ADHERENCE": "1", "BLOCKID": "76", "BLOCK_ABBR": "12-9", "DIRECTION": "Northbound", "LATITUDE": "33.7902106", "LONGITUDE": "-84.411972", "MSGTIME": "4/16/2018 6:47:55 PM", "ROUTE": "12", "STOPID": "904800", "TIMEPOINT": "Midtown Station", "TRIPID": "6146252", "VEHICLE": "2515"}, {"ADHERENCE": "-3", "BLOCKID": "405", "BLOCK_ABBR": "60-4", "DIRECTION": "Northbound", "LATITUDE": "33.8135082", "LONGITUDE": "-84.4686032", "MSGTIME": "4/16/2018 6:48:00 PM", "ROUTE": "60", "STOPID": "901800", "TIMEPOINT": "Hollywood Rd & Arno Dr", "TRIPID": "6151922", "VEHICLE": "2511"}, {"ADHERENCE": "0", "BLOCKID": "9", "BLOCK_ABBR": "103-4", "DIRECTION": "Northbound", "LATITUDE": "33.8886161", "LONGITUDE": "-84.2552194", "MSGTIME": "4/16/2018 6:48:01 PM", "ROUTE": "103", "STOPID": "211173", "TIMEPOINT": "Peeler Rd & Winters Chapel Rd", "TRIPID": "0", "VEHICLE": "1427"}, {"ADHERENCE": "0", "BLOCKID": "364", "BLOCK_ABBR": "5-1", "DIRECTION": "Southbound", "LATITUDE": "33.8236163", "LONGITUDE": "-84.3698361", "MSGTIME": "4/16/2018 6:48:01 PM", "ROUTE": "5", "STOPID": "902145", "TIMEPOINT": "Lindbergh Ctr Station (N Loop)", "TRIPID": "6168294", "VEHICLE": "2506"}, {"ADHERENCE": "1", "BLOCKID": "370", "BLOCK_ABBR": "5-7", "DIRECTION": "Northbound", "LATITUDE": "33.8870107", "LONGITUDE": "-84.3816116", "MSGTIME": "4/16/2018 6:48:13 PM", "ROUTE": "5", "STOPID": "905429", "TIMEPOINT": "Piedmont Rd & Peachtree Rd", "TRIPID": "6151265", "VEHICLE": "1472"}, {"ADHERENCE": "-2", "BLOCKID": "120", "BLOCK_ABBR": "14-3", "DIRECTION": "Westbound", "LATITUDE": "33.8193295", "LONGITUDE": "-84.4511566", "MSGTIME": "4/16/2018 6:48:21 PM", "ROUTE": "37", "STOPID": "901897", "TIMEPOINT": "Defoor Ave & Collier Rd", "TRIPID": "6164629", "VEHICLE": "1568"}, {"ADHERENCE": "-2", "BLOCKID": "572", "BLOCK_ABBR": "93-2", "DIRECTION": "Westbound", "LATITUDE": "33.6781103", "LONGITUDE": "-84.4401369", "MSGTIME": "4/16/2018 6:48:25 PM", "ROUTE": "93", "STOPID": "166901", "TIMEPOINT": "College Pk Station (North Loop)", "TRIPID": "6156972", "VEHICLE": "2345"}, {"ADHERENCE": "-2", "BLOCKID": "34", "BLOCK_ABBR": "115-15", "DIRECTION": "Eastbound", "LATITUDE": "33.6937037", "LONGITUDE": "-84.0962532", "MSGTIME": "4/16/2018 6:48:35 PM", "ROUTE": "115", "STOPID": "133148", "TIMEPOINT": "Covington Hwy & Chupp Rd", "TRIPID": "6169853", "VEHICLE": "1625"}, {"ADHERENCE": "-10", "BLOCKID": "476", "BLOCK_ABBR": "82-2", "DIRECTION": "Eastbound", "LATITUDE": "33.6184749", "LONGITUDE": "-84.552201", "MSGTIME": "4/16/2018 6:48:39 PM", "ROUTE": "82", "STOPID": "213381", "TIMEPOINT": "Derrick Ind Pkwy @ Walmart Dist", "TRIPID": "6160207", "VEHICLE": "1817"}, {"ADHERENCE": "4", "BLOCKID": "21", "BLOCK_ABBR": "109-2", "DIRECTION": "Northbound", "LATITUDE": "33.7505104", "LONGITUDE": "-84.386284", "MSGTIME": "4/16/2018 6:48:43 PM", "ROUTE": "109", "STOPID": "210709", "TIMEPOINT": "Georgia State Station (West)", "TRIPID": "6169815", "VEHICLE": "1570"}, {"ADHERENCE": "0", "BLOCKID": "541", "BLOCK_ABBR": "86-7", "DIRECTION": "Eastbound", "LATITUDE": "33.6916833", "LONGITUDE": "-84.0885366", "MSGTIME": "4/16/2018 6:48:51 PM", "ROUTE": "86", "STOPID": "211293", "TIMEPOINT": "Hillandale Dr & Hillandale Pk Dr", "TRIPID": "6157296", "VEHICLE": "1612"}, {"ADHERENCE": "-2", "BLOCKID": "511", "BLOCK_ABBR": "85-12", "DIRECTION": "Southbound", "LATITUDE": "34.0009863", "LONGITUDE": "-84.3505378", "MSGTIME": "4/16/2018 6:48:54 PM", "ROUTE": "85", "STOPID": "210484", "TIMEPOINT": "Alpharetta Hwy & Commerce Pkwy", "TRIPID": "6142052", "VEHICLE": "2530"}, {"ADHERENCE": "-3", "BLOCKID": "442", "BLOCK_ABBR": "75-3", "DIRECTION": "Northbound", "LATITUDE": "33.858054", "LONGITUDE": "-84.1986323", "MSGTIME": "4/16/2018 6:49:02 PM", "ROUTE": "75", "STOPID": "210149", "TIMEPOINT": "Mtn Ind Blvd & Tuckerstone Pkwy", "TRIPID": "6148809", "VEHICLE": "1410"}, {"ADHERENCE": "-1", "BLOCKID": "281", "BLOCK_ABBR": "26-3", "DIRECTION": "Southbound", "LATITUDE": "33.8083132", "LONGITUDE": "-84.4760436", "MSGTIME": "4/16/2018 6:49:07 PM", "ROUTE": "26", "STOPID": "210300", "TIMEPOINT": "Bolton Rd & Parrot Ave", "TRIPID": "6176182", "VEHICLE": "2529"}, {"ADHERENCE": "-1", "BLOCKID": "367", "BLOCK_ABBR": "5-4", "DIRECTION": "Southbound", "LATITUDE": "31.8327198", "LONGITUDE": "-84.255546", "MSGTIME": "4/16/2018 6:49:26 PM", "ROUTE": "5", "STOPID": "903009", "TIMEPOINT": "Dunwoody Station", "TRIPID": "6168296", "VEHICLE": "1467"}, {"ADHERENCE": "0", "BLOCKID": "191", "BLOCK_ABBR": "186-2", "DIRECTION": "Eastbound", "LATITUDE": "33.7148884", "LONGITUDE": "-84.2127729", "MSGTIME": "4/16/2018 6:49:28 PM", "ROUTE": "186", "STOPID": "211898", "TIMEPOINT": "Snapfinger Woods @ GA Piedmont", "TRIPID": "6157954", "VEHICLE": "1508"}, {"ADHERENCE": "0", "BLOCKID": "382", "BLOCK_ABBR": "51-8", "DIRECTION": "Northbound", "LATITUDE": "33.7544136", "LONGITUDE": "-84.4688442", "MSGTIME": "4/16/2018 6:49:36 PM", "ROUTE": "51", "STOPID": "903320", "TIMEPOINT": "Hamilton E Holmes Station", "TRIPID": "6178232", "VEHICLE": "1678"}, {"ADHERENCE": "1", "BLOCKID": "410", "BLOCK_ABBR": "71-1", "DIRECTION": "Eastbound", "LATITUDE": "33.7222693", "LONGITUDE": "-84.4609021", "MSGTIME": "4/16/2018 6:50:11 PM", "ROUTE": "71", "STOPID": "120084", "TIMEPOINT": "Cascade Rd & Fairburn Rd", "TRIPID": "6148763", "VEHICLE": "2548"}, {"ADHERENCE": "-2", "BLOCKID": "96", "BLOCK_ABBR": "121-8", "DIRECTION": "Southbound", "LATITUDE": "33.785769", "LONGITUDE": "-84.2347367", "MSGTIME": "4/16/2018 6:50:14 PM", "ROUTE": "121", "STOPID": "211710", "TIMEPOINT": "Memorial Dr & N Hairston Rd", "TRIPID": "6160773", "VEHICLE": "1556"}, {"ADHERENCE": "-4", "BLOCKID": "415", "BLOCK_ABBR": "71-4", "DIRECTION": "Westbound", "LATITUDE": "33.7370413", "LONGITUDE": "-84.4358684", "MSGTIME": "4/16/2018 6:50:18 PM", "ROUTE": "71", "STOPID": "114900", "TIMEPOINT": "West End Station", "TRIPID": "6169194", "VEHICLE": "1587"}, {"ADHERENCE": "-2", "BLOCKID": "509", "BLOCK_ABBR": "85-10", "DIRECTION": "Northbound", "LATITUDE": "33.7893947", "LONGITUDE": "-84.4414908", "MSGTIME": "4/16/2018 6:50:25 PM", "ROUTE": "85", "STOPID": "902651", "TIMEPOINT": "Dunwoody Pl & Roswell Rd", "TRIPID": "6156940", "VEHICLE": "2521"}, {"ADHERENCE": "0", "BLOCKID": "65", "BLOCK_ABBR": "12-1", "DIRECTION": "Northbound", "LATITUDE": "33.8781132", "LONGITUDE": "-84.469222", "MSGTIME": "4/16/2018 6:50:29 PM", "ROUTE": "12", "STOPID": "900079", "TIMEPOINT": "Cumberland Transfer Center", "TRIPID": "6146251", "VEHICLE": "1488"}, {"ADHERENCE": "0", "BLOCKID": "385", "BLOCK_ABBR": "55-2", "DIRECTION": "Southbound", "LATITUDE": "33.616067", "LONGITUDE": "-84.352715", "MSGTIME": "4/16/2018 6:50:33 PM", "ROUTE": "55", "STOPID": "212353", "TIMEPOINT": "Forest Pkwy & Bartlett Dr", "TRIPID": "6145103", "VEHICLE": "2386"}, {"ADHERENCE": "0", "BLOCKID": "407", "BLOCK_ABBR": "66-2", "DIRECTION": "Southbound", "LATITUDE": "33.6567642", "LONGITUDE": "-84.5115974", "MSGTIME": "4/16/2018 6:50:43 PM", "ROUTE": "66", "STOPID": "144130", "TIMEPOINT": "N Camp Creek Pkwy & Darrah Dr", "TRIPID": "6155247", "VEHICLE": "1580"}, {"ADHERENCE": "1", "BLOCKID": "66", "BLOCK_ABBR": "12-10", "DIRECTION": "Southbound", "LATITUDE": "33.7814432", "LONGITUDE": "-84.3978761", "MSGTIME": "4/16/2018 6:50:44 PM", "ROUTE": "12", "STOPID": "901719", "TIMEPOINT": "Howell Mill Rd & Trabert Ave", "TRIPID": "6142190", "VEHICLE": "1473"}, {"ADHERENCE": "0", "BLOCKID": "424", "BLOCK_ABBR": "73-12", "DIRECTION": "Southbound", "LATITUDE": "33.7263166", "LONGITUDE": "-84.5903326", "MSGTIME": "4/16/2018 6:50:52 PM", "ROUTE": "73", "STOPID": "901290", "TIMEPOINT": "LaGrange Blvd & Boat Rock Blvd", "TRIPID": "6152226", "VEHICLE": "2415"}, {"ADHERENCE": "0", "BLOCKID": "48", "BLOCK_ABBR": "117-12", "DIRECTION": "Northbound", "LATITUDE": "33.7823032", "LONGITUDE": "-84.2734738", "MSGTIME": "4/16/2018 6:50:53 PM", "ROUTE": "117", "STOPID": "903587", "TIMEPOINT": "North Decatur Rd & Church St", "TRIPID": "6171141", "VEHICLE": "1436"}, {"ADHERENCE": "7", "BLOCKID": "189", "BLOCK_ABBR": "186-1", "DIRECTION": "Westbound", "LATITUDE": "33.7435564", "LONGITUDE": "-84.3625716", "MSGTIME": "4/16/2018 6:51:04 PM", "ROUTE": "186", "STOPID": "130122", "TIMEPOINT": "Rainbow Dr & Candler Rd", "TRIPID": "6173718", "VEHICLE": "1415"}, {"ADHERENCE": "-6", "BLOCKID": "215", "BLOCK_ABBR": "192-1", "DIRECTION": "Northbound", "LATITUDE": "33.5344016", "LONGITUDE": "-84.3641444", "MSGTIME": "4/16/2018 6:51:12 PM", "ROUTE": "192", "STOPID": "212236", "TIMEPOINT": "Clayton County Justice Center", "TRIPID": "6173119", "VEHICLE": "2302"}, {"ADHERENCE": "-7", "BLOCKID": "237", "BLOCK_ABBR": "196-8", "DIRECTION": "Southbound", "LATITUDE": "33.5733311", "LONGITUDE": "-84.3718232", "MSGTIME": "4/16/2018 6:51:19 PM", "ROUTE": "196", "STOPID": "212148", "TIMEPOINT": "Southern Regional Medical Center", "TRIPID": "6149658", "VEHICLE": "1707"}, {"ADHERENCE": "4", "BLOCKID": "278", "BLOCK_ABBR": "25-4", "DIRECTION": "Northbound", "LATITUDE": "33.8594199", "LONGITUDE": "-84.3395026", "MSGTIME": "4/16/2018 6:51:22 PM", "ROUTE": "25", "STOPID": "905666", "TIMEPOINT": "Lenox Station", "TRIPID": "6141979", "VEHICLE": "1519"}, {"ADHERENCE": "-1", "BLOCKID": "528", "BLOCK_ABBR": "86-1", "DIRECTION": "Westbound", "LATITUDE": "33.762637", "LONGITUDE": "-84.2177256", "MSGTIME": "4/16/2018 6:51:25 PM", "ROUTE": "86", "STOPID": "109022", "TIMEPOINT": "Hairston Rd & Covington Hwy", "TRIPID": "6161220", "VEHICLE": "2563"}, {"ADHERENCE": "0", "BLOCKID": "129", "BLOCK_ABBR": "141-3", "DIRECTION": "Northbound", "LATITUDE": "34.0906995", "LONGITUDE": "-84.2753972", "MSGTIME": "4/16/2018 6:51:34 PM", "ROUTE": "141", "STOPID": "902977", "TIMEPOINT": "Main St & Windward Pkwy", "TRIPID": "6145950", "VEHICLE": "1571"}, {"ADHERENCE": "0", "BLOCKID": "512", "BLOCK_ABBR": "85-2", "DIRECTION": "Northbound", "LATITUDE": "34.0348146", "LONGITUDE": "-84.3452332", "MSGTIME": "4/16/2018 6:51:34 PM", "ROUTE": "85", "STOPID": "903177", "TIMEPOINT": "Mansell Park & Ride", "TRIPID": "6165739", "VEHICLE": "1653"}, {"ADHERENCE": "30", "BLOCKID": "230", "BLOCK_ABBR": "196-10", "DIRECTION": "Southbound", "LATITUDE": "33.5554022", "LONGITUDE": "-84.4148633", "MSGTIME": "4/16/2018 6:51:36 PM", "ROUTE": "196", "STOPID": "212104", "TIMEPOINT": "Garden Walk Blvd & Riverdale Rd", "TRIPID": "6142474", "VEHICLE": "1704"}, {"ADHERENCE": "-8", "BLOCKID": "453", "BLOCK_ABBR": "78-7", "DIRECTION": "Westbound", "LATITUDE": "33.6519255", "LONGITUDE": "-84.3943828", "MSGTIME": "4/16/2018 6:51:37 PM", "ROUTE": "78", "STOPID": "146900", "TIMEPOINT": "East Point Station", "TRIPID": "0", "VEHICLE": "2395"}, {"ADHERENCE": "0", "BLOCKID": "86", "BLOCK_ABBR": "120-7", "DIRECTION": "Westbound", "LATITUDE": "33.7757732", "LONGITUDE": "-84.2815428", "MSGTIME": "4/16/2018 6:51:41 PM", "ROUTE": "120", "STOPID": "904264", "TIMEPOINT": "Avondale Station (North Loop)", "TRIPID": "6170875", "VEHICLE": "2327"}, {"ADHERENCE": "0", "BLOCKID": "421", "BLOCK_ABBR": "73-1", "DIRECTION": "Southbound", "LATITUDE": "33.7360203", "LONGITUDE": "-84.5650612", "MSGTIME": "4/16/2018 6:51:43 PM", "ROUTE": "73", "STOPID": "212876", "TIMEPOINT": "Westpark Pl & Westpark Dr", "TRIPID": "6145178", "VEHICLE": "1446"}, {"ADHERENCE": "-2", "BLOCKID": "337", "BLOCK_ABBR": "39-6", "DIRECTION": "Southbound", "LATITUDE": "33.8231962", "LONGITUDE": "-84.3697349", "MSGTIME": "4/16/2018 6:51:50 PM", "ROUTE": "39", "STOPID": "902145", "TIMEPOINT": "Lindbergh Ctr Station (N Loop)", "TRIPID": "6141460", "VEHICLE": "1706"}, {"ADHERENCE": "0", "BLOCKID": "234", "BLOCK_ABBR": "196-5", "DIRECTION": "Southbound", "LATITUDE": "33.5737462", "LONGITUDE": "-84.3499856", "MSGTIME": "4/16/2018 6:51:53 PM", "ROUTE": "196", "STOPID": "212168", "TIMEPOINT": "Southlake Mall", "TRIPID": "6142468", "VEHICLE": "1650"}, {"ADHERENCE": "-10", "BLOCKID": "297", "BLOCK_ABBR": "3-4", "DIRECTION": "Eastbound", "LATITUDE": "33.7487743", "LONGITUDE": "-84.4174976", "MSGTIME": "4/16/2018 6:51:58 PM", "ROUTE": "3", "STOPID": "114900", "TIMEPOINT": "West End Station", "TRIPID": "6142564", "VEHICLE": "1572"}, {"ADHERENCE": "-1", "BLOCKID": "387", "BLOCK_ABBR": "55-4", "DIRECTION": "Southbound", "LATITUDE": "33.7057343", "LONGITUDE": "-84.3791129", "MSGTIME": "4/16/2018 6:52:00 PM", "ROUTE": "55", "STOPID": "115168", "TIMEPOINT": "Hank Aaron Dr & Atlanta Ave", "TRIPID": "6151896", "VEHICLE": "2408"}, {"ADHERENCE": "2", "BLOCKID": "371", "BLOCK_ABBR": "5-8", "DIRECTION": "Northbound", "LATITUDE": "33.8357651", "LONGITUDE": "-84.3679102", "MSGTIME": "4/16/2018 6:52:05 PM", "ROUTE": "5", "STOPID": "902145", "TIMEPOINT": "Lindbergh Ctr Station (N Loop)", "TRIPID": "6155676", "VEHICLE": "1672"}, {"ADHERENCE": "1", "BLOCKID": "83", "BLOCK_ABBR": "120-4", "DIRECTION": "Eastbound", "LATITUDE": "33.8117126", "LONGITUDE": "-84.2383406", "MSGTIME": "4/16/2018 6:52:08 PM", "ROUTE": "120", "STOPID": "213051", "TIMEPOINT": "Ponce de Leon Ave & Decatur Rd", "TRIPID": "6145903", "VEHICLE": "2581"}, {"ADHERENCE": "0", "BLOCKID": "50", "BLOCK_ABBR": "117-14", "DIRECTION": "Northbound", "LATITUDE": "33.7904742", "LONGITUDE": "-84.1771751", "MSGTIME": "4/16/2018 6:52:11 PM", "ROUTE": "117", "STOPID": "210025", "TIMEPOINT": "Panola Rd & Redan Rd", "TRIPID": "6153159", "VEHICLE": "1409"}, {"ADHERENCE": "0", "BLOCKID": "233", "BLOCK_ABBR": "196-4", "DIRECTION": "Northbound", "LATITUDE": "33.5699983", "LONGITUDE": "-84.4030191", "MSGTIME": "4/16/2018 6:52:15 PM", "ROUTE": "196", "STOPID": "212141", "TIMEPOINT": "L Hutcheson Pky & Valley Hill Rd", "TRIPID": "6177468", "VEHICLE": "1712"}, {"ADHERENCE": "0", "BLOCKID": "19", "BLOCK_ABBR": "107-8", "DIRECTION": "Eastbound", "LATITUDE": "33.7681692", "LONGITUDE": "-84.2514075", "MSGTIME": "4/16/2018 6:52:27 PM", "ROUTE": "107", "STOPID": "211300", "TIMEPOINT": "Indian Creek Station (West Loop)", "TRIPID": "6152855", "VEHICLE": "1641"}, {"ADHERENCE": "0", "BLOCKID": "320", "BLOCK_ABBR": "34-1", "DIRECTION": "Northbound", "LATITUDE": "33.7755412", "LONGITUDE": "-84.2821558", "MSGTIME": "4/16/2018 6:52:28 PM", "ROUTE": "114", "STOPID": "904264", "TIMEPOINT": "Avondale Station (North Loop)", "TRIPID": "6149362", "VEHICLE": "2593"}, {"ADHERENCE": "-2", "BLOCKID": "108", "BLOCK_ABBR": "125-3", "DIRECTION": "Southbound", "LATITUDE": "33.8104767", "LONGITUDE": "-84.241658", "MSGTIME": "4/16/2018 6:52:36 PM", "ROUTE": "125", "STOPID": "210382", "TIMEPOINT": "Northlake Pkwy & E Exchange Pl", "TRIPID": "6161544", "VEHICLE": "1506"}, {"ADHERENCE": "-1", "BLOCKID": "536", "BLOCK_ABBR": "86-2", "DIRECTION": "Westbound", "LATITUDE": "33.7661189", "LONGITUDE": "-84.2617511", "MSGTIME": "4/16/2018 6:52:37 PM", "ROUTE": "86", "STOPID": "900686", "TIMEPOINT": "Kensington Station", "TRIPID": "6178456", "VEHICLE": "1513"}, {"ADHERENCE": "-20", "BLOCKID": "4", "BLOCK_ABBR": "1-4", "DIRECTION": "Northbound", "LATITUDE": "33.775677", "LONGITUDE": "-84.4070669", "MSGTIME": "4/16/2018 6:52:38 PM", "ROUTE": "1", "STOPID": "901263", "TIMEPOINT": "Vine City Station", "TRIPID": "6160915", "VEHICLE": "2539"}, {"ADHERENCE": "0", "BLOCKID": "87", "BLOCK_ABBR": "120-8", "DIRECTION": "Eastbound", "LATITUDE": "33.8108909", "LONGITUDE": "-84.183206", "MSGTIME": "4/16/2018 6:52:40 PM", "ROUTE": "120", "STOPID": "211482", "TIMEPOINT": "Memorial Drive Park & Ride", "TRIPID": "6145897", "VEHICLE": "1422"}, {"ADHERENCE": "-3", "BLOCKID": "411", "BLOCK_ABBR": "71-10", "DIRECTION": "Westbound", "LATITUDE": "33.7198439", "LONGITUDE": "-84.4731662", "MSGTIME": "4/16/2018 6:52:44 PM", "ROUTE": "71", "STOPID": "900177", "TIMEPOINT": "Cascade Ave & Beecher St", "TRIPID": "6141557", "VEHICLE": "2513"}, {"ADHERENCE": "-3", "BLOCKID": "366", "BLOCK_ABBR": "5-3", "DIRECTION": "Southbound", "LATITUDE": "33.9007852", "LONGITUDE": "-84.3799185", "MSGTIME": "4/16/2018 6:52:48 PM", "ROUTE": "5", "STOPID": "902751", "TIMEPOINT": "Roswell Rd & Hammond Dr", "TRIPID": "6145518", "VEHICLE": "2501"}, {"ADHERENCE": "-5", "BLOCKID": "550", "BLOCK_ABBR": "87-7", "DIRECTION": "Southbound", "LATITUDE": "33.9895498", "LONGITUDE": "-84.3419495", "MSGTIME": "4/16/2018 6:52:49 PM", "ROUTE": "87", "STOPID": "902725", "TIMEPOINT": "North Springs Station", "TRIPID": "6149280", "VEHICLE": "1651"}, {"ADHERENCE": "0", "BLOCKID": "472", "BLOCK_ABBR": "813-3", "DIRECTION": "Eastbound", "LATITUDE": "33.7495375", "LONGITUDE": "-84.3854275", "MSGTIME": "4/16/2018 6:52:53 PM", "ROUTE": "813", "STOPID": "210431", "TIMEPOINT": "Georgia State Station (East)", "TRIPID": "6177118", "VEHICLE": "2322"}, {"ADHERENCE": "0", "BLOCKID": "571", "BLOCK_ABBR": "93-1", "DIRECTION": "Eastbound", "LATITUDE": "33.6522722", "LONGITUDE": "-84.4489668", "MSGTIME": "4/16/2018 6:52:55 PM", "ROUTE": "93", "STOPID": "166901", "TIMEPOINT": "College Pk Station (North Loop)", "TRIPID": "6160485", "VEHICLE": "2346"}, {"ADHERENCE": "6", "BLOCKID": "483", "BLOCK_ABBR": "823-1", "DIRECTION": "Northbound", "LATITUDE": "33.767676", "LONGITUDE": "-84.2962908", "MSGTIME": "4/16/2018 6:52:59 PM", "ROUTE": "823", "STOPID": "904654", "TIMEPOINT": "S Candler St & Midway Rd", "TRIPID": "6173971", "VEHICLE": "1657"}, {"ADHERENCE": "0", "BLOCKID": "289", "BLOCK_ABBR": "27-7", "DIRECTION": "Northbound", "LATITUDE": "33.8083184", "LONGITUDE": "-84.3662552", "MSGTIME": "4/16/2018 6:53:01 PM", "ROUTE": "27", "STOPID": "213258", "TIMEPOINT": "Piedmont Ave & Monroe Dr", "TRIPID": "6168598", "VEHICLE": "2508"}, {"ADHERENCE": "0", "BLOCKID": "38", "BLOCK_ABBR": "115-3", "DIRECTION": "Eastbound", "LATITUDE": "33.6989549", "LONGITUDE": "-84.0992234", "MSGTIME": "4/16/2018 6:53:06 PM", "ROUTE": "115", "STOPID": "134088", "TIMEPOINT": "Mall at Stonecrest", "TRIPID": "6157320", "VEHICLE": "1633"}, {"ADHERENCE": "0", "BLOCKID": "106", "BLOCK_ABBR": "125-1", "DIRECTION": "Southbound", "LATITUDE": "33.7837734", "LONGITUDE": "-84.2678886", "MSGTIME": "4/16/2018 6:53:09 PM", "ROUTE": "125", "STOPID": "900686", "TIMEPOINT": "Kensington Station", "TRIPID": "6145930", "VEHICLE": "2573"}, {"ADHERENCE": "0", "BLOCKID": "27", "BLOCK_ABBR": "110-6", "DIRECTION": "Southbound", "LATITUDE": "33.7892469", "LONGITUDE": "-84.3868049", "MSGTIME": "4/16/2018 6:53:14 PM", "ROUTE": "110", "STOPID": "901789", "TIMEPOINT": "Arts Center Station", "TRIPID": "6152871", "VEHICLE": "1459"}, {"ADHERENCE": "-1", "BLOCKID": "413", "BLOCK_ABBR": "71-2", "DIRECTION": "Westbound", "LATITUDE": "33.7343237", "LONGITUDE": "-84.5321516", "MSGTIME": "4/16/2018 6:53:15 PM", "ROUTE": "71", "STOPID": "900861", "TIMEPOINT": "Country Squire Apartments", "TRIPID": "6152207", "VEHICLE": "2516"}, {"ADHERENCE": "0", "BLOCKID": "51", "BLOCK_ABBR": "117-15", "DIRECTION": "Southbound", "LATITUDE": "33.7865299", "LONGITUDE": "-84.2192783", "MSGTIME": "4/16/2018 6:53:16 PM", "ROUTE": "117", "STOPID": "904252", "TIMEPOINT": "North Decatur Rd & Church St", "TRIPID": "6161252", "VEHICLE": "2571"}, {"ADHERENCE": "-10", "BLOCKID": "103", "BLOCK_ABBR": "124-4", "DIRECTION": "Westbound", "LATITUDE": "33.8839688", "LONGITUDE": "-84.2203096", "MSGTIME": "4/16/2018 6:53:19 PM", "ROUTE": "124", "STOPID": "211570", "TIMEPOINT": "Lawerenceville Hwy & H Howell Rd", "TRIPID": "6149426", "VEHICLE": "1552"}, {"ADHERENCE": "-9", "BLOCKID": "279", "BLOCK_ABBR": "26-1", "DIRECTION": "Southbound", "LATITUDE": "33.7725658", "LONGITUDE": "-84.4285282", "MSGTIME": "4/16/2018 6:53:21 PM", "ROUTE": "26", "STOPID": "902019", "TIMEPOINT": "Perry Blvd @ MARTA", "TRIPID": "6168588", "VEHICLE": "2524"}, {"ADHERENCE": "-4", "BLOCKID": "399", "BLOCK_ABBR": "6-7", "DIRECTION": "Southbound", "LATITUDE": "33.7721447", "LONGITUDE": "-84.2893058", "MSGTIME": "4/16/2018 6:53:24 PM", "ROUTE": "6", "STOPID": "901155", "TIMEPOINT": "Inman Park Station (North Loop)", "TRIPID": "0", "VEHICLE": "2576"}, {"ADHERENCE": "-3", "BLOCKID": "441", "BLOCK_ABBR": "75-2", "DIRECTION": "Northbound", "LATITUDE": "33.7944224", "LONGITUDE": "-84.2765374", "MSGTIME": "4/16/2018 6:53:31 PM", "ROUTE": "75", "STOPID": "904264", "TIMEPOINT": "Avondale Station (North Loop)", "TRIPID": "6169219", "VEHICLE": "1526"}, {"ADHERENCE": "-8", "BLOCKID": "35", "BLOCK_ABBR": "115-16", "DIRECTION": "Eastbound", "LATITUDE": "33.7441975", "LONGITUDE": "-84.1291114", "MSGTIME": "4/16/2018 6:53:34 PM", "ROUTE": "115", "STOPID": "903453", "TIMEPOINT": "Redan Rd & Martin Rd", "TRIPID": "6171936", "VEHICLE": "1551"}, {"ADHERENCE": "0", "BLOCKID": "545", "BLOCK_ABBR": "87-2", "DIRECTION": "Northbound", "LATITUDE": "33.9525702", "LONGITUDE": "-84.3578464", "MSGTIME": "4/16/2018 6:53:41 PM", "ROUTE": "87", "STOPID": "902725", "TIMEPOINT": "North Springs Station", "TRIPID": "6153487", "VEHICLE": "1475"}, {"ADHERENCE": "0", "BLOCKID": "300", "BLOCK_ABBR": "3-7", "DIRECTION": "Eastbound", "LATITUDE": "33.738009", "LONGITUDE": "-84.4355647", "MSGTIME": "4/16/2018 6:53:44 PM", "ROUTE": "3", "STOPID": "122316", "TIMEPOINT": "Beecher Rd & Benjamin E Mays Dr", "TRIPID": "6152182", "VEHICLE": "1481"}, {"ADHERENCE": "1", "BLOCKID": "159", "BLOCK_ABBR": "15-7", "DIRECTION": "Southbound", "LATITUDE": "33.6971922", "LONGITUDE": "-84.2713986", "MSGTIME": "4/16/2018 6:53:55 PM", "ROUTE": "15", "STOPID": "130062", "TIMEPOINT": "Candler Rd & Rainbow Way", "TRIPID": "6155708", "VEHICLE": "1606"}, {"ADHERENCE": "1", "BLOCKID": "40", "BLOCK_ABBR": "115-5", "DIRECTION": "Eastbound", "LATITUDE": "33.7163168", "LONGITUDE": "-84.1304229", "MSGTIME": "4/16/2018 6:53:58 PM", "ROUTE": "115", "STOPID": "133052", "TIMEPOINT": "Covington Hwy & Panola Rd", "TRIPID": "6161241", "VEHICLE": "1418"}, {"ADHERENCE": "-2", "BLOCKID": "474", "BLOCK_ABBR": "813-5", "DIRECTION": "Eastbound", "LATITUDE": "33.7659309", "LONGITUDE": "-84.4323464", "MSGTIME": "4/16/2018 6:54:01 PM", "ROUTE": "813", "STOPID": "903936", "TIMEPOINT": "Baker Rd & Center Hill Ave", "TRIPID": "6149828", "VEHICLE": "2339"}, {"ADHERENCE": "-1", "BLOCKID": "53", "BLOCK_ABBR": "117-2", "DIRECTION": "Northbound", "LATITUDE": "33.7212248", "LONGITUDE": "-84.1660568", "MSGTIME": "4/16/2018 6:54:08 PM", "ROUTE": "117", "STOPID": "210346", "TIMEPOINT": "GRTA Park & Ride", "TRIPID": "6149388", "VEHICLE": "2578"}, {"ADHERENCE": "-1", "BLOCKID": "170", "BLOCK_ABBR": "16-3", "DIRECTION": "Southbound", "LATITUDE": "33.7767432", "LONGITUDE": "-84.3525357", "MSGTIME": "4/16/2018 6:54:11 PM", "ROUTE": "16", "STOPID": "901174", "TIMEPOINT": "Johnson Rd & Briarcliff Rd", "TRIPID": "6173044", "VEHICLE": "1417"}, {"ADHERENCE": "0", "BLOCKID": "322", "BLOCK_ABBR": "34-3", "DIRECTION": "Northbound", "LATITUDE": "33.7646498", "LONGITUDE": "-84.3127701", "MSGTIME": "4/16/2018 6:54:12 PM", "ROUTE": "34", "STOPID": "904323", "TIMEPOINT": "East Lake Station (South Loop)", "TRIPID": "6164619", "VEHICLE": "2557"}, {"ADHERENCE": "-1", "BLOCKID": "37", "BLOCK_ABBR": "115-2", "DIRECTION": "Westbound", "LATITUDE": "33.7062914", "LONGITUDE": "-84.1140125", "MSGTIME": "4/16/2018 6:54:18 PM", "ROUTE": "115", "STOPID": "134088", "TIMEPOINT": "Mall at Stonecrest", "TRIPID": "6171061", "VEHICLE": "1642"}, {"ADHERENCE": "1", "BLOCKID": "551", "BLOCK_ABBR": "87-8", "DIRECTION": "Northbound", "LATITUDE": "33.9743707", "LONGITUDE": "-84.3551134", "MSGTIME": "4/16/2018 6:54:19 PM", "ROUTE": "87", "STOPID": "902853", "TIMEPOINT": "Roswell Rd & Dalrymple Rd", "TRIPID": "6171587", "VEHICLE": "1583"}, {"ADHERENCE": "1", "BLOCKID": "406", "BLOCK_ABBR": "66-1", "DIRECTION": "Northbound", "LATITUDE": "33.6748799", "LONGITUDE": "-84.4968792", "MSGTIME": "4/16/2018 6:54:26 PM", "ROUTE": "66", "STOPID": "144118", "TIMEPOINT": "N Camp Creek Pkwy & Darrah Dr", "TRIPID": "6170731", "VEHICLE": "1451"}, {"ADHERENCE": "0", "BLOCKID": "566", "BLOCK_ABBR": "9-2", "DIRECTION": "Southbound", "LATITUDE": "33.7113858", "LONGITUDE": "-84.2710308", "MSGTIME": "4/16/2018 6:54:27 PM", "ROUTE": "9", "STOPID": "130050", "TIMEPOINT": "Candler Rd & Rainbow Way", "TRIPID": "6174039", "VEHICLE": "1618"}, {"ADHERENCE": "0", "BLOCKID": "200", "BLOCK_ABBR": "189-2", "DIRECTION": "Northbound", "LATITUDE": "33.6349413", "LONGITUDE": "-84.4643163", "MSGTIME": "4/16/2018 6:54:30 PM", "ROUTE": "189", "STOPID": "211077", "TIMEPOINT": "Old Natl Hwy & Godby Rd", "TRIPID": "6153812", "VEHICLE": "2375"}, {"ADHERENCE": "0", "BLOCKID": "565", "BLOCK_ABBR": "9-1", "DIRECTION": "Northbound", "LATITUDE": "33.7561463", "LONGITUDE": "-84.3525212", "MSGTIME": "4/16/2018 6:54:38 PM", "ROUTE": "9", "STOPID": "901066", "TIMEPOINT": "Inman Park Station (South Loop)", "TRIPID": "6168320", "VEHICLE": "1649"}, {"ADHERENCE": "8", "BLOCKID": "553", "BLOCK_ABBR": "89-1", "DIRECTION": "Southbound", "LATITUDE": "33.5680382", "LONGITUDE": "-84.5267882", "MSGTIME": "4/16/2018 6:54:44 PM", "ROUTE": "89", "STOPID": "211051", "TIMEPOINT": "Jonesboro Rd & Old Natl Hwy", "TRIPID": "6156967", "VEHICLE": "2376"}, {"ADHERENCE": "0", "BLOCKID": "531", "BLOCK_ABBR": "86-12", "DIRECTION": "Eastbound", "LATITUDE": "33.7149469", "LONGITUDE": "-84.2167989", "MSGTIME": "4/16/2018 6:54:48 PM", "ROUTE": "86", "STOPID": "107284", "TIMEPOINT": "Columbia Dr & Snapfinger Rd", "TRIPID": "6160229", "VEHICLE": "1619"}, {"ADHERENCE": "1", "BLOCKID": "186", "BLOCK_ABBR": "180-4", "DIRECTION": "Southbound", "LATITUDE": "33.6026569", "LONGITUDE": "-84.5404905", "MSGTIME": "4/16/2018 6:54:48 PM", "ROUTE": "180", "STOPID": "176150", "TIMEPOINT": "Roosevelt Hwy & Buffington Rd", "TRIPID": "6153544", "VEHICLE": "2369"}, {"ADHERENCE": "-5", "BLOCKID": "318", "BLOCK_ABBR": "32-6", "DIRECTION": "Northbound", "LATITUDE": "33.7065502", "LONGITUDE": "-84.4036378", "MSGTIME": "4/16/2018 6:54:50 PM", "ROUTE": "32", "STOPID": "102274", "TIMEPOINT": "Alabama St & Forsyth St", "TRIPID": "6168601", "VEHICLE": "2385"}, {"ADHERENCE": "-1", "BLOCKID": "402", "BLOCK_ABBR": "60-1", "DIRECTION": "Northbound", "LATITUDE": "33.7997905", "LONGITUDE": "-84.4869991", "MSGTIME": "4/16/2018 6:54:50 PM", "ROUTE": "60", "STOPID": "903868", "TIMEPOINT": "James Jackson Py & Hightower Rd", "TRIPID": "6153509", "VEHICLE": "1455"}, {"ADHERENCE": "2", "BLOCKID": "295", "BLOCK_ABBR": "3-2", "DIRECTION": "Eastbound", "LATITUDE": "33.75101", "LONGITUDE": "-84.3929584", "MSGTIME": "4/16/2018 6:54:56 PM", "ROUTE": "3", "STOPID": "100137", "TIMEPOINT": "MLK Jr Dr & Whitehouse Dr", "TRIPID": "6168118", "VEHICLE": "2543"}, {"ADHERENCE": "-6", "BLOCKID": "277", "BLOCK_ABBR": "25-3", "DIRECTION": "Southbound", "LATITUDE": "33.9104355", "LONGITUDE": "-84.2846597", "MSGTIME": "4/16/2018 6:55:04 PM", "ROUTE": "25", "STOPID": "905508", "TIMEPOINT": "Doraville Station", "TRIPID": "6145577", "VEHICLE": "1425"}, {"ADHERENCE": "-2", "BLOCKID": "3", "BLOCK_ABBR": "1-3", "DIRECTION": "Northbound", "LATITUDE": "33.7460209", "LONGITUDE": "-84.4066647", "MSGTIME": "4/16/2018 6:55:20 PM", "ROUTE": "1", "STOPID": "114900", "TIMEPOINT": "West End Station", "TRIPID": "6160916", "VEHICLE": "1659"}, {"ADHERENCE": "2", "BLOCKID": "12", "BLOCK_ABBR": "107-1", "DIRECTION": "Westbound", "LATITUDE": "33.739998", "LONGITUDE": "-84.3329456", "MSGTIME": "4/16/2018 6:55:21 PM", "ROUTE": "107", "STOPID": "106238", "TIMEPOINT": "Candler Rd & Glenwood Rd", "TRIPID": "6152849", "VEHICLE": "1607"}, {"ADHERENCE": "-1", "BLOCKID": "49", "BLOCK_ABBR": "117-13", "DIRECTION": "Southbound", "LATITUDE": "33.7258955", "LONGITUDE": "-84.1673007", "MSGTIME": "4/16/2018 6:55:22 PM", "ROUTE": "117", "STOPID": "210024", "TIMEPOINT": "Panola Rd & Redan Rd", "TRIPID": "6174613", "VEHICLE": "1543"}, {"ADHERENCE": "9", "BLOCKID": "26", "BLOCK_ABBR": "110-5", "DIRECTION": "Southbound", "LATITUDE": "33.8457959", "LONGITUDE": "-84.3574846", "MSGTIME": "4/16/2018 6:55:23 PM", "ROUTE": "110", "STOPID": "905666", "TIMEPOINT": "Lenox Station", "TRIPID": "6157288", "VEHICLE": "1663"}, {"ADHERENCE": "-3", "BLOCKID": "459", "BLOCK_ABBR": "8-2", "DIRECTION": "Southbound", "LATITUDE": "33.791227", "LONGITUDE": "-84.2563865", "MSGTIME": "4/16/2018 6:55:25 PM", "ROUTE": "8", "STOPID": "903818", "TIMEPOINT": "Druid Hills Rd & Lawrenceville", "TRIPID": "6167942", "VEHICLE": "1509"}, {"ADHERENCE": "1", "BLOCKID": "298", "BLOCK_ABBR": "3-5", "DIRECTION": "Westbound", "LATITUDE": "33.754218", "LONGITUDE": "-84.4765879", "MSGTIME": "4/16/2018 6:55:28 PM", "ROUTE": "3", "STOPID": "900812", "TIMEPOINT": "Scott St & Brownlee Rd", "TRIPID": "6156360", "VEHICLE": "1452"}, {"ADHERENCE": "-6", "BLOCKID": "581", "BLOCK_ABBR": "99-2", "DIRECTION": "Northbound", "LATITUDE": "33.7554601", "LONGITUDE": "-84.3739225", "MSGTIME": "4/16/2018 6:55:29 PM", "ROUTE": "99", "STOPID": "103900", "TIMEPOINT": "King Memorial Station", "TRIPID": "6142109", "VEHICLE": "2351"}, {"ADHERENCE": "0", "BLOCKID": "153", "BLOCK_ABBR": "15-1", "DIRECTION": "Northbound", "LATITUDE": "33.7745289", "LONGITUDE": "-84.2977469", "MSGTIME": "4/16/2018 6:55:30 PM", "ROUTE": "15", "STOPID": "904262", "TIMEPOINT": "Decatur Station", "TRIPID": "6174044", "VEHICLE": "1639"}, {"ADHERENCE": "-6", "BLOCKID": "341", "BLOCK_ABBR": "4-1", "DIRECTION": "Northbound", "LATITUDE": "33.6910156", "LONGITUDE": "-84.3543325", "MSGTIME": "4/16/2018 6:55:31 PM", "ROUTE": "4", "STOPID": "151059", "TIMEPOINT": "Constitution Rd & Jonesboro Rd", "TRIPID": "6159736", "VEHICLE": "1503"}, {"ADHERENCE": "-2", "BLOCKID": "22", "BLOCK_ABBR": "110-1", "DIRECTION": "Northbound", "LATITUDE": "33.8367886", "LONGITUDE": "-84.3814322", "MSGTIME": "4/16/2018 6:55:39 PM", "ROUTE": "110", "STOPID": "900456", "TIMEPOINT": "Peachtree Rd & Peachtree Hills", "TRIPID": "6149352", "VEHICLE": "2518"}, {"ADHERENCE": "0", "BLOCKID": "116", "BLOCK_ABBR": "132-3", "DIRECTION": "Northbound", "LATITUDE": "33.9360189", "LONGITUDE": "-84.2940157", "MSGTIME": "4/16/2018 6:55:47 PM", "ROUTE": "132", "STOPID": "773140", "TIMEPOINT": "N Peachtree Rd & Peeler Rd", "TRIPID": "6145939", "VEHICLE": "1613"}, {"ADHERENCE": "-2", "BLOCKID": "131", "BLOCK_ABBR": "141-5", "DIRECTION": "Southbound", "LATITUDE": "34.0880352", "LONGITUDE": "-84.2631875", "MSGTIME": "4/16/2018 6:55:50 PM", "ROUTE": "141", "STOPID": "902641", "TIMEPOINT": "Windward Park & Ride", "TRIPID": "6176364", "VEHICLE": "1576"}, {"ADHERENCE": "0", "BLOCKID": "23", "BLOCK_ABBR": "110-2", "DIRECTION": "Northbound", "LATITUDE": "33.8023149", "LONGITUDE": "-84.3927241", "MSGTIME": "4/16/2018 6:55:53 PM", "ROUTE": "110", "STOPID": "901789", "TIMEPOINT": "Arts Center Station", "TRIPID": "6161207", "VEHICLE": "2541"}, {"ADHERENCE": "0", "BLOCKID": "394", "BLOCK_ABBR": "6-2", "DIRECTION": "Northbound", "LATITUDE": "33.8233213", "LONGITUDE": "-84.3695204", "MSGTIME": "4/16/2018 6:55:56 PM", "ROUTE": "6", "STOPID": "902145", "TIMEPOINT": "Lindbergh Ctr Station (N Loop)", "TRIPID": "6173831", "VEHICLE": "2494"}, {"ADHERENCE": "1", "BLOCKID": "445", "BLOCK_ABBR": "75-6", "DIRECTION": "Southbound", "LATITUDE": "33.8119509", "LONGITUDE": "-84.2789496", "MSGTIME": "4/16/2018 6:55:57 PM", "ROUTE": "75", "STOPID": "901526", "TIMEPOINT": "Lawrenceville Hwy & McLendon Dr", "TRIPID": "6152240", "VEHICLE": "2575"}, {"ADHERENCE": "2", "BLOCKID": "355", "BLOCK_ABBR": "47-4", "DIRECTION": "Southbound", "LATITUDE": "33.84104", "LONGITUDE": "-84.3130113", "MSGTIME": "4/16/2018 6:55:58 PM", "ROUTE": "47", "STOPID": "211324", "TIMEPOINT": "I-85 Access Rd & Shallowford Rd", "TRIPID": "6149272", "VEHICLE": "1536"}, {"ADHERENCE": "-3", "BLOCKID": "464", "BLOCK_ABBR": "81-1", "DIRECTION": "Southbound", "LATITUDE": "33.7152992", "LONGITUDE": "-84.4414541", "MSGTIME": "4/16/2018 6:55:58 PM", "ROUTE": "81", "STOPID": "123140", "TIMEPOINT": "Avon Ave & Wyland Dr", "TRIPID": "6145224", "VEHICLE": "2304"}, {"ADHERENCE": "0", "BLOCKID": "350", "BLOCK_ABBR": "42-2", "DIRECTION": "Northbound", "LATITUDE": "33.7466658", "LONGITUDE": "-84.3929934", "MSGTIME": "4/16/2018 6:55:59 PM", "ROUTE": "42", "STOPID": "115018", "TIMEPOINT": "Pryor Rd & Doane St", "TRIPID": "6168886", "VEHICLE": "2361"}, {"ADHERENCE": "-1", "BLOCKID": "425", "BLOCK_ABBR": "73-2", "DIRECTION": "Northbound", "LATITUDE": "33.7579817", "LONGITUDE": "-84.5032677", "MSGTIME": "4/16/2018 6:56:02 PM", "ROUTE": "73", "STOPID": "903743", "TIMEPOINT": "Fulton Ind Blvd & MLK Jr Dr", "TRIPID": "6141566", "VEHICLE": "2519"}, {"ADHERENCE": "2", "BLOCKID": "428", "BLOCK_ABBR": "73-5", "DIRECTION": "Northbound", "LATITUDE": "33.7598215", "LONGITUDE": "-84.5394935", "MSGTIME": "4/16/2018 6:56:12 PM", "ROUTE": "73", "STOPID": "901325", "TIMEPOINT": "Fulton Ind Blvd & Cascade Rd", "TRIPID": "6148783", "VEHICLE": "1447"}, {"ADHERENCE": "-3", "BLOCKID": "577", "BLOCK_ABBR": "95-4", "DIRECTION": "Southbound", "LATITUDE": "33.6554693", "LONGITUDE": "-84.3994306", "MSGTIME": "4/16/2018 6:56:15 PM", "ROUTE": "95", "STOPID": "148092", "TIMEPOINT": "King Arnold St & Sunset Dr", "TRIPID": "6149318", "VEHICLE": "2397"}, {"ADHERENCE": "0", "BLOCKID": "374", "BLOCK_ABBR": "50-3", "DIRECTION": "Westbound", "LATITUDE": "33.7766006", "LONGITUDE": "-84.4567086", "MSGTIME": "4/16/2018 6:56:17 PM", "ROUTE": "50", "STOPID": "904519", "TIMEPOINT": "Bankhead Station", "TRIPID": "6158936", "VEHICLE": "1483"}, {"ADHERENCE": "5", "BLOCKID": "104", "BLOCK_ABBR": "124-5", "DIRECTION": "Eastbound", "LATITUDE": "33.8553404", "LONGITUDE": "-84.2169842", "MSGTIME": "4/16/2018 6:56:19 PM", "ROUTE": "124", "STOPID": "906160", "TIMEPOINT": "Pleasantdale & Tucker-Norcross", "TRIPID": "6171366", "VEHICLE": "1420"}, {"ADHERENCE": "4", "BLOCKID": "354", "BLOCK_ABBR": "47-3", "DIRECTION": "Northbound", "LATITUDE": "33.8381826", "LONGITUDE": "-84.3218567", "MSGTIME": "4/16/2018 6:56:21 PM", "ROUTE": "47", "STOPID": "905259", "TIMEPOINT": "Briarwood Rd & Buford Hwy", "TRIPID": "6151872", "VEHICLE": "1504"}, {"ADHERENCE": "-3", "BLOCKID": "344", "BLOCK_ABBR": "40-2", "DIRECTION": "Southbound", "LATITUDE": "33.7627634", "LONGITUDE": "-84.387176", "MSGTIME": "4/16/2018 6:56:21 PM", "ROUTE": "40", "STOPID": "905031", "TIMEPOINT": "Peachtree St & North Ave", "TRIPID": "6168883", "VEHICLE": "1658"}, {"ADHERENCE": "0", "BLOCKID": "259", "BLOCK_ABBR": "21-3", "DIRECTION": "Eastbound", "LATITUDE": "33.7700196", "LONGITUDE": "-84.2505853", "MSGTIME": "4/16/2018 6:56:25 PM", "ROUTE": "21", "STOPID": "107346", "TIMEPOINT": "Memorial Dr & Columbia Dr", "TRIPID": "6141963", "VEHICLE": "1426"}, {"ADHERENCE": "2", "BLOCKID": "157", "BLOCK_ABBR": "15-5", "DIRECTION": "Northbound", "LATITUDE": "33.6334822", "LONGITUDE": "-84.2832525", "MSGTIME": "4/16/2018 6:56:26 PM", "ROUTE": "15", "STOPID": "212217", "TIMEPOINT": "Bouldercrest Rd & Panola Rd", "TRIPID": "6151282", "VEHICLE": "1620"}, {"ADHERENCE": "0", "BLOCKID": "99", "BLOCK_ABBR": "123-2", "DIRECTION": "Northbound", "LATITUDE": "33.8099845", "LONGITUDE": "-84.2773524", "MSGTIME": "4/16/2018 6:56:27 PM", "ROUTE": "123", "STOPID": "903671", "TIMEPOINT": "North DeKalb Mall", "TRIPID": "6157600", "VEHICLE": "1610"}, {"ADHERENCE": "1", "BLOCKID": "168", "BLOCK_ABBR": "16-1", "DIRECTION": "Northbound", "LATITUDE": "33.8447951", "LONGITUDE": "-84.3587884", "MSGTIME": "4/16/2018 6:56:30 PM", "ROUTE": "16", "STOPID": "905666", "TIMEPOINT": "Lenox Station", "TRIPID": "6145559", "VEHICLE": "1549"}, {"ADHERENCE": "-2", "BLOCKID": "62", "BLOCK_ABBR": "119-2", "DIRECTION": "Eastbound", "LATITUDE": "33.762405", "LONGITUDE": "-84.2159609", "MSGTIME": "4/16/2018 6:56:32 PM", "ROUTE": "119", "STOPID": "903391", "TIMEPOINT": "Indian Creek Station (East Loop)", "TRIPID": "6145806", "VEHICLE": "1429"}, {"ADHERENCE": "-2", "BLOCKID": "574", "BLOCK_ABBR": "95-1", "DIRECTION": "Southbound", "LATITUDE": "33.7026483", "LONGITUDE": "-84.4081349", "MSGTIME": "4/16/2018 6:56:37 PM", "ROUTE": "95", "STOPID": "124052", "TIMEPOINT": "Metropolitan Pky @ Atlanta Tech", "TRIPID": "6156989", "VEHICLE": "2374"}, {"ADHERENCE": "-3", "BLOCKID": "573", "BLOCK_ABBR": "93-3", "DIRECTION": "Eastbound", "LATITUDE": "33.6745757", "LONGITUDE": "-84.4970219", "MSGTIME": "4/16/2018 6:56:42 PM", "ROUTE": "93", "STOPID": "145075", "TIMEPOINT": "N Camp Crk Pkwy @ Stone Pk Apts", "TRIPID": "6152571", "VEHICLE": "2344"}, {"ADHERENCE": "2", "BLOCKID": "552", "BLOCK_ABBR": "87-9", "DIRECTION": "Northbound", "LATITUDE": "33.9812049", "LONGITUDE": "-84.3421245", "MSGTIME": "4/16/2018 6:56:42 PM", "ROUTE": "87", "STOPID": "902725", "TIMEPOINT": "North Springs Station", "TRIPID": "6142374", "VEHICLE": "2354"}, {"ADHERENCE": "1", "BLOCKID": "141", "BLOCK_ABBR": "143-11", "DIRECTION": "Southbound", "LATITUDE": "34.0844496", "LONGITUDE": "-84.2641077", "MSGTIME": "4/16/2018 6:56:55 PM", "ROUTE": "143", "STOPID": "210826", "TIMEPOINT": "Deerfield Pkwy & Webb Rd", "TRIPID": "6176305", "VEHICLE": "2502"}, {"ADHERENCE": "3", "BLOCKID": "238", "BLOCK_ABBR": "196-9", "DIRECTION": "Southbound", "LATITUDE": "33.5555619", "LONGITUDE": "-84.4151019", "MSGTIME": "4/16/2018 6:56:58 PM", "ROUTE": "196", "STOPID": "166900", "TIMEPOINT": "College Pk Station (South Loop)", "TRIPID": "6177115", "VEHICLE": "1701"}, {"ADHERENCE": "-1", "BLOCKID": "20", "BLOCK_ABBR": "109-1", "DIRECTION": "Northbound", "LATITUDE": "33.7809075", "LONGITUDE": "-84.386527", "MSGTIME": "4/16/2018 6:57:00 PM", "ROUTE": "109", "STOPID": "904800", "TIMEPOINT": "Midtown Station", "TRIPID": "6160538", "VEHICLE": "2514"}, {"ADHERENCE": "-2", "BLOCKID": "544", "BLOCK_ABBR": "87-1", "DIRECTION": "Northbound", "LATITUDE": "33.9190174", "LONGITUDE": "-84.3504255", "MSGTIME": "4/16/2018 6:57:01 PM", "ROUTE": "87", "STOPID": "903009", "TIMEPOINT": "Dunwoody Station", "TRIPID": "6160888", "VEHICLE": "1684"}, {"ADHERENCE": "2", "BLOCKID": "369", "BLOCK_ABBR": "5-6", "DIRECTION": "Northbound", "LATITUDE": "33.9203378", "LONGITUDE": "-84.3656462", "MSGTIME": "4/16/2018 6:57:04 PM", "ROUTE": "5", "STOPID": "906308", "TIMEPOINT": "Roswell Rd & Hammond Dr", "TRIPID": "6167939", "VEHICLE": "1679"}, {"ADHERENCE": "-1", "BLOCKID": "54", "BLOCK_ABBR": "117-3", "DIRECTION": "Northbound", "LATITUDE": "33.7860744", "LONGITUDE": "-84.244363", "MSGTIME": "4/16/2018 6:57:06 PM", "ROUTE": "117", "STOPID": "903060", "TIMEPOINT": "Rockbridge Rd & Indian Creek Dr", "TRIPID": "6160364", "VEHICLE": "2590"}, {"ADHERENCE": "0", "BLOCKID": "109", "BLOCK_ABBR": "125-4", "DIRECTION": "Northbound", "LATITUDE": "33.8497661", "LONGITUDE": "-84.2587247", "MSGTIME": "4/16/2018 6:57:07 PM", "ROUTE": "125", "STOPID": "900278", "TIMEPOINT": "Briarcliff Rd & Randolph Rd", "TRIPID": "6160797", "VEHICLE": "1507"}, {"ADHERENCE": "-1", "BLOCKID": "14", "BLOCK_ABBR": "107-3", "DIRECTION": "Westbound", "LATITUDE": "33.7508163", "LONGITUDE": "-84.2288965", "MSGTIME": "4/16/2018 6:57:08 PM", "ROUTE": "107", "STOPID": "211300", "TIMEPOINT": "Indian Creek Station (West Loop)", "TRIPID": "6175706", "VEHICLE": "1434"}, {"ADHERENCE": "-1", "BLOCKID": "180", "BLOCK_ABBR": "178-2", "DIRECTION": "Southbound", "LATITUDE": "33.6629326", "LONGITUDE": "-84.3860755", "MSGTIME": "4/16/2018 6:57:12 PM", "ROUTE": "178", "STOPID": "159344", "TIMEPOINT": "Hamilton Blvd @ MARTA", "TRIPID": "6173109", "VEHICLE": "2336"}, {"ADHERENCE": "-2", "BLOCKID": "208", "BLOCK_ABBR": "19-5", "DIRECTION": "Northbound", "LATITUDE": "33.8684892", "LONGITUDE": "-84.3094074", "MSGTIME": "4/16/2018 6:57:14 PM", "ROUTE": "19", "STOPID": "905213", "TIMEPOINT": "Clairmont Rd & Buford Hwy", "TRIPID": "6151548", "VEHICLE": "1559"}, {"ADHERENCE": "-4", "BLOCKID": "468", "BLOCK_ABBR": "81-5", "DIRECTION": "Northbound", "LATITUDE": "33.7245416", "LONGITUDE": "-84.4016554", "MSGTIME": "4/16/2018 6:57:14 PM", "ROUTE": "81", "STOPID": "125030", "TIMEPOINT": "Ridge Ave & Pulliam St", "TRIPID": "6145972", "VEHICLE": "2310"}, {"ADHERENCE": "-1", "BLOCKID": "378", "BLOCK_ABBR": "51-4", "DIRECTION": "Eastbound", "LATITUDE": "33.7634816", "LONGITUDE": "-84.4262536", "MSGTIME": "4/16/2018 6:57:15 PM", "ROUTE": "51", "STOPID": "211374", "TIMEPOINT": "Joseph E Boone Bvd & W Lake Ave", "TRIPID": "6146233", "VEHICLE": "1477"}, {"ADHERENCE": "-3", "BLOCKID": "93", "BLOCK_ABBR": "121-5", "DIRECTION": "Northbound", "LATITUDE": "33.8339829", "LONGITUDE": "-84.21372", "MSGTIME": "4/16/2018 6:57:15 PM", "ROUTE": "121", "STOPID": "901618", "TIMEPOINT": "Ponce de Leon Ave & Hairston Rd", "TRIPID": "6175928", "VEHICLE": "2583"}, {"ADHERENCE": "0", "BLOCKID": "176", "BLOCK_ABBR": "162-2", "DIRECTION": "Eastbound", "LATITUDE": "33.7129312", "LONGITUDE": "-84.438885", "MSGTIME": "4/16/2018 6:57:17 PM", "ROUTE": "162", "STOPID": "122138", "TIMEPOINT": "Stanton Rd & Sweetbriar Cir", "TRIPID": "6149580", "VEHICLE": "2315"}, {"ADHERENCE": "-3", "BLOCKID": "13", "BLOCK_ABBR": "107-2", "DIRECTION": "Eastbound", "LATITUDE": "33.7400499", "LONGITUDE": "-84.3386076", "MSGTIME": "4/16/2018 6:57:18 PM", "ROUTE": "107", "STOPID": "104012", "TIMEPOINT": "Glenwood Ave & Moreland Ave", "TRIPID": "6175704", "VEHICLE": "1534"}, {"ADHERENCE": "0", "BLOCKID": "18", "BLOCK_ABBR": "107-7", "DIRECTION": "Westbound", "LATITUDE": "33.7560205", "LONGITUDE": "-84.3524664", "MSGTIME": "4/16/2018 6:57:18 PM", "ROUTE": "107", "STOPID": "901066", "TIMEPOINT": "Inman Park Station (South Loop)", "TRIPID": "6160536", "VEHICLE": "2577"}, {"ADHERENCE": "0", "BLOCKID": "216", "BLOCK_ABBR": "192-2", "DIRECTION": "Northbound", "LATITUDE": "33.6773471", "LONGITUDE": "-84.4404532", "MSGTIME": "4/16/2018 6:57:19 PM", "ROUTE": "192", "STOPID": "146900", "TIMEPOINT": "East Point Station", "TRIPID": "6149642", "VEHICLE": "2318"}, {"ADHERENCE": "0", "BLOCKID": "262", "BLOCK_ABBR": "21-6", "DIRECTION": "Eastbound", "LATITUDE": "33.7473539", "LONGITUDE": "-84.3260083", "MSGTIME": "4/16/2018 6:57:20 PM", "ROUTE": "21", "STOPID": "104050", "TIMEPOINT": "Memorial Dr & Moreland Dr", "TRIPID": "6175594", "VEHICLE": "2560"}, {"ADHERENCE": "-2", "BLOCKID": "326", "BLOCK_ABBR": "34-7", "DIRECTION": "Southbound", "LATITUDE": "33.7284337", "LONGITUDE": "-84.2520446", "MSGTIME": "4/16/2018 6:57:22 PM", "ROUTE": "114", "STOPID": "107098", "TIMEPOINT": "Columbia Dr & Glenwood Rd", "TRIPID": "6142171", "VEHICLE": "2585"}, {"ADHERENCE": "-1", "BLOCKID": "52", "BLOCK_ABBR": "117-16", "DIRECTION": "Southbound", "LATITUDE": "33.7041581", "LONGITUDE": "-84.1957418", "MSGTIME": "4/16/2018 6:57:25 PM", "ROUTE": "117", "STOPID": "210346", "TIMEPOINT": "GRTA Park & Ride", "TRIPID": "6169863", "VEHICLE": "1501"}, {"ADHERENCE": "0", "BLOCKID": "1", "BLOCK_ABBR": "1-1", "DIRECTION": "Southbound", "LATITUDE": "33.7361555", "LONGITUDE": "-84.4134577", "MSGTIME": "4/16/2018 6:57:27 PM", "ROUTE": "1", "STOPID": "114900", "TIMEPOINT": "West End Station", "TRIPID": "6141881", "VEHICLE": "2503"}, {"ADHERENCE": "-4", "BLOCKID": "327", "BLOCK_ABBR": "34-8", "DIRECTION": "Southbound", "LATITUDE": "33.7088328", "LONGITUDE": "-84.3126893", "MSGTIME": "4/16/2018 6:57:28 PM", "ROUTE": "34", "STOPID": "900110", "TIMEPOINT": "Gresham Rd & Flat Shoals Rd", "TRIPID": "6175880", "VEHICLE": "1533"}, {"ADHERENCE": "-1", "BLOCKID": "338", "BLOCK_ABBR": "39-7", "DIRECTION": "Southbound", "LATITUDE": "33.8893976", "LONGITUDE": "-84.286351", "MSGTIME": "4/16/2018 6:57:28 PM", "ROUTE": "39", "STOPID": "905508", "TIMEPOINT": "Doraville Station", "TRIPID": "6141461", "VEHICLE": "1516"}, {"ADHERENCE": "-5", "BLOCKID": "274", "BLOCK_ABBR": "24-4", "DIRECTION": "Westbound", "LATITUDE": "33.7536309", "LONGITUDE": "-84.338619", "MSGTIME": "4/16/2018 6:57:31 PM", "ROUTE": "24", "STOPID": "105208", "TIMEPOINT": "Hosea Williams Dr & Howard St", "TRIPID": "6168420", "VEHICLE": "1631"}, {"ADHERENCE": "4", "BLOCKID": "178", "BLOCK_ABBR": "172-2", "DIRECTION": "Southbound", "LATITUDE": "33.6524102", "LONGITUDE": "-84.4487164", "MSGTIME": "4/16/2018 6:57:33 PM", "ROUTE": "172", "STOPID": "166901", "TIMEPOINT": "College Pk Station (North Loop)", "TRIPID": "6175956", "VEHICLE": "2343"}, {"ADHERENCE": "-2", "BLOCKID": "47", "BLOCK_ABBR": "117-11", "DIRECTION": "Southbound", "LATITUDE": "33.7902822", "LONGITUDE": "-84.1716145", "MSGTIME": "4/16/2018 6:57:38 PM", "ROUTE": "117", "STOPID": "906089", "TIMEPOINT": "Rockbridge Rd & Hairston Rd", "TRIPID": "6170871", "VEHICLE": "1531"}, {"ADHERENCE": "0", "BLOCKID": "377", "BLOCK_ABBR": "51-3", "DIRECTION": "Westbound", "LATITUDE": "33.7544336", "LONGITUDE": "-84.4690083", "MSGTIME": "4/16/2018 6:57:41 PM", "ROUTE": "51", "STOPID": "903320", "TIMEPOINT": "Hamilton E Holmes Station", "TRIPID": "6154755", "VEHICLE": "1584"}, {"ADHERENCE": "4", "BLOCKID": "148", "BLOCK_ABBR": "143-7", "DIRECTION": "Northbound", "LATITUDE": "34.0858328", "LONGITUDE": "-84.2607593", "MSGTIME": "4/16/2018 6:57:42 PM", "ROUTE": "143", "STOPID": "902641", "TIMEPOINT": "Windward Park & Ride", "TRIPID": "6145961", "VEHICLE": "1562"}, {"ADHERENCE": "-2", "BLOCKID": "513", "BLOCK_ABBR": "85-3", "DIRECTION": "Northbound", "LATITUDE": "33.9554052", "LONGITUDE": "-84.3567085", "MSGTIME": "4/16/2018 6:57:44 PM", "ROUTE": "185", "STOPID": "902725", "TIMEPOINT": "North Springs Station", "TRIPID": "6161130", "VEHICLE": "2534"}, {"ADHERENCE": "-4", "BLOCKID": "538", "BLOCK_ABBR": "86-4", "DIRECTION": "Westbound", "LATITUDE": "33.703792", "LONGITUDE": "-84.1829167", "MSGTIME": "4/16/2018 6:57:44 PM", "ROUTE": "86", "STOPID": "210346", "TIMEPOINT": "GRTA Park & Ride", "TRIPID": "6171581", "VEHICLE": "1512"}, {"ADHERENCE": "-9", "BLOCKID": "395", "BLOCK_ABBR": "6-3", "DIRECTION": "Southbound", "LATITUDE": "33.7856831", "LONGITUDE": "-84.3408559", "MSGTIME": "4/16/2018 6:57:45 PM", "ROUTE": "6", "STOPID": "902218", "TIMEPOINT": "N Decatur Rd & Oxford Rd", "TRIPID": "6170979", "VEHICLE": "2582"}, {"ADHERENCE": "3", "BLOCKID": "2", "BLOCK_ABBR": "1-2", "DIRECTION": "Northbound", "LATITUDE": "33.7991384", "LONGITUDE": "-84.4345214", "MSGTIME": "4/16/2018 6:57:47 PM", "ROUTE": "1", "STOPID": "213388", "TIMEPOINT": "W Marietta St & Joseph Lowery Bv", "TRIPID": "6175551", "VEHICLE": "2536"}, {"ADHERENCE": "0", "BLOCKID": "408", "BLOCK_ABBR": "66-3", "DIRECTION": "Northbound", "LATITUDE": "33.7550201", "LONGITUDE": "-84.4666288", "MSGTIME": "4/16/2018 6:57:49 PM", "ROUTE": "66", "STOPID": "903320", "TIMEPOINT": "Hamilton E Holmes Station", "TRIPID": "6175811", "VEHICLE": "1460"}, {"ADHERENCE": "0", "BLOCKID": "117", "BLOCK_ABBR": "132-4", "DIRECTION": "Southbound", "LATITUDE": "33.8886602", "LONGITUDE": "-84.3057909", "MSGTIME": "4/16/2018 6:57:51 PM", "ROUTE": "132", "STOPID": "905515", "TIMEPOINT": "Chamblee Station (West Loop)", "TRIPID": "6166586", "VEHICLE": "1524"}, {"ADHERENCE": "-4", "BLOCKID": "70", "BLOCK_ABBR": "12-3", "DIRECTION": "Southbound", "LATITUDE": "33.8289529", "LONGITUDE": "-84.4159466", "MSGTIME": "4/16/2018 6:57:53 PM", "ROUTE": "12", "STOPID": "900080", "TIMEPOINT": "Howell Mill Rd @ Paces Pavilion", "TRIPID": "6162837", "VEHICLE": "1478"}, {"ADHERENCE": "0", "BLOCKID": "381", "BLOCK_ABBR": "51-7", "DIRECTION": "Southbound", "LATITUDE": "33.7475811", "LONGITUDE": "-84.5084864", "MSGTIME": "4/16/2018 6:57:56 PM", "ROUTE": "51", "STOPID": "905973", "TIMEPOINT": "MLK Jr Dr & Brownlee Rd", "TRIPID": "6149852", "VEHICLE": "1662"}, {"ADHERENCE": "0", "BLOCKID": "373", "BLOCK_ABBR": "50-2", "DIRECTION": "Eastbound", "LATITUDE": "33.7716101", "LONGITUDE": "-84.3865665", "MSGTIME": "4/16/2018 6:57:58 PM", "ROUTE": "50", "STOPID": "907473", "TIMEPOINT": "North Ave Station", "TRIPID": "6146263", "VEHICLE": "2505"}, {"ADHERENCE": "0", "BLOCKID": "429", "BLOCK_ABBR": "73-6", "DIRECTION": "Northbound", "LATITUDE": "33.7545818", "LONGITUDE": "-84.4691561", "MSGTIME": "4/16/2018 6:57:58 PM", "ROUTE": "73", "STOPID": "903320", "TIMEPOINT": "Hamilton E Holmes Station", "TRIPID": "6156381", "VEHICLE": "2547"}, {"ADHERENCE": "-3", "BLOCKID": "570", "BLOCK_ABBR": "9-6", "DIRECTION": "Southbound", "LATITUDE": "33.7324083", "LONGITUDE": "-84.3385704", "MSGTIME": "4/16/2018 6:57:59 PM", "ROUTE": "9", "STOPID": "105474", "TIMEPOINT": "Flat Shoals Ave & Glenwood Ave", "TRIPID": "6164300", "VEHICLE": "2561"}, {"ADHERENCE": "-1", "BLOCKID": "458", "BLOCK_ABBR": "8-1", "DIRECTION": "Northbound", "LATITUDE": "33.7907658", "LONGITUDE": "-84.2549575", "MSGTIME": "4/16/2018 6:58:02 PM", "ROUTE": "8", "STOPID": "903855", "TIMEPOINT": "Clarendon Ave & Cedar St", "TRIPID": "6146133", "VEHICLE": "1437"}, {"ADHERENCE": "-1", "BLOCKID": "304", "BLOCK_ABBR": "30-10", "DIRECTION": "Eastbound", "LATITUDE": "33.8469248", "LONGITUDE": "-84.2498387", "MSGTIME": "4/16/2018 6:58:09 PM", "ROUTE": "30", "STOPID": "900278", "TIMEPOINT": "Briarcliff Rd & Randolph Rd", "TRIPID": "0", "VEHICLE": "2325"}, {"ADHERENCE": "-4", "BLOCKID": "334", "BLOCK_ABBR": "39-3", "DIRECTION": "Southbound", "LATITUDE": "33.8567402", "LONGITUDE": "-84.3134726", "MSGTIME": "4/16/2018 6:58:12 PM", "ROUTE": "39", "STOPID": "906139", "TIMEPOINT": "Buford Hwy & Clairmont Rd", "TRIPID": "6164634", "VEHICLE": "1716"}, {"ADHERENCE": "0", "BLOCKID": "24", "BLOCK_ABBR": "110-3", "DIRECTION": "Southbound", "LATITUDE": "33.8078491", "LONGITUDE": "-84.3938035", "MSGTIME": "4/16/2018 6:58:13 PM", "ROUTE": "110", "STOPID": "900644", "TIMEPOINT": "Peachtree Rd & Peachtree Hills", "TRIPID": "6157287", "VEHICLE": "2533"}, {"ADHERENCE": "-1", "BLOCKID": "311", "BLOCK_ABBR": "30-8", "DIRECTION": "Northbound", "LATITUDE": "33.8697813", "LONGITUDE": "-84.2902002", "MSGTIME": "4/16/2018 6:58:24 PM", "ROUTE": "33", "STOPID": "906060", "TIMEPOINT": "Shallowford Rd & I-85", "TRIPID": "6141442", "VEHICLE": "1411"}, {"ADHERENCE": "0", "BLOCKID": "448", "BLOCK_ABBR": "78-2", "DIRECTION": "Westbound", "LATITUDE": "33.6627716", "LONGITUDE": "-84.3850029", "MSGTIME": "4/16/2018 6:58:25 PM", "ROUTE": "78", "STOPID": "159128", "TIMEPOINT": "Cleveland Ave & Browns Mill Rd", "TRIPID": "6175484", "VEHICLE": "2358"}, {"ADHERENCE": "2", "BLOCKID": "154", "BLOCK_ABBR": "15-2", "DIRECTION": "Northbound", "LATITUDE": "33.7444279", "LONGITUDE": "-84.2906954", "MSGTIME": "4/16/2018 6:58:29 PM", "ROUTE": "15", "STOPID": "106118", "TIMEPOINT": "Candler Rd & Glenwood Rd", "TRIPID": "6149160", "VEHICLE": "1626"}, {"ADHERENCE": "-9", "BLOCKID": "347", "BLOCK_ABBR": "40-5", "DIRECTION": "Northbound", "LATITUDE": "33.7762379", "LONGITUDE": "-84.3845136", "MSGTIME": "4/16/2018 6:58:32 PM", "ROUTE": "40", "STOPID": "904673", "TIMEPOINT": "Peachtree St & North Ave", "TRIPID": "6173744", "VEHICLE": "1482"}, {"ADHERENCE": "0", "BLOCKID": "192", "BLOCK_ABBR": "186-3", "DIRECTION": "Eastbound", "LATITUDE": "33.7097324", "LONGITUDE": "-84.2688168", "MSGTIME": "4/16/2018 6:58:34 PM", "ROUTE": "186", "STOPID": "130178", "TIMEPOINT": "Rainbow Dr & Candler Rd", "TRIPID": "6174852", "VEHICLE": "2564"}, {"ADHERENCE": "-5", "BLOCKID": "164", "BLOCK_ABBR": "150-3", "DIRECTION": "Eastbound", "LATITUDE": "33.9264848", "LONGITUDE": "-84.3378509", "MSGTIME": "4/16/2018 6:58:35 PM", "ROUTE": "150", "STOPID": "902891", "TIMEPOINT": "Ashford-Dunwoody & Perimeter Ctr", "TRIPID": "6173678", "VEHICLE": "1676"}, {"ADHERENCE": "1", "BLOCKID": "391", "BLOCK_ABBR": "55-8", "DIRECTION": "Southbound", "LATITUDE": "33.6430097", "LONGITUDE": "-84.3631772", "MSGTIME": "4/16/2018 6:58:41 PM", "ROUTE": "55", "STOPID": "167016", "TIMEPOINT": "Jonesboro Rd & Conley Rd (N end)", "TRIPID": "6175274", "VEHICLE": "2340"}, {"ADHERENCE": "-1", "BLOCKID": "119", "BLOCK_ABBR": "14-2", "DIRECTION": "Eastbound", "LATITUDE": "33.8046824", "LONGITUDE": "-84.4220607", "MSGTIME": "4/16/2018 6:58:42 PM", "ROUTE": "37", "STOPID": "901667", "TIMEPOINT": "Defoor Ave & Collier Rd", "TRIPID": "6156024", "VEHICLE": "1466"}, {"ADHERENCE": "0", "BLOCKID": "258", "BLOCK_ABBR": "21-2", "DIRECTION": "Westbound", "LATITUDE": "33.7499906", "LONGITUDE": "-84.3850801", "MSGTIME": "4/16/2018 6:58:43 PM", "ROUTE": "21", "STOPID": "210431", "TIMEPOINT": "Georgia State Station (East)", "TRIPID": "6155979", "VEHICLE": "1621"}, {"ADHERENCE": "-5", "BLOCKID": "392", "BLOCK_ABBR": "55-9", "DIRECTION": "Northbound", "LATITUDE": "33.654034", "LONGITUDE": "-84.3564787", "MSGTIME": "4/16/2018 6:58:45 PM", "ROUTE": "55", "STOPID": "212194", "TIMEPOINT": "Jonesboro Rd & Conley Rd (N end)", "TRIPID": "6151902", "VEHICLE": "1724"}, {"ADHERENCE": "-4", "BLOCKID": "229", "BLOCK_ABBR": "196-1", "DIRECTION": "Southbound", "LATITUDE": "33.5733316", "LONGITUDE": "-84.4028649", "MSGTIME": "4/16/2018 6:58:45 PM", "ROUTE": "196", "STOPID": "212139", "TIMEPOINT": "L Hutcheson Pky & Valley Hill Rd", "TRIPID": "6149659", "VEHICLE": "1703"}, {"ADHERENCE": "0", "BLOCKID": "510", "BLOCK_ABBR": "85-11", "DIRECTION": "Southbound", "LATITUDE": "34.0709742", "LONGITUDE": "-84.2970098", "MSGTIME": "4/16/2018 6:58:47 PM", "ROUTE": "185", "STOPID": "905753", "TIMEPOINT": "Haynes Bridge Rd & Old Milton Py", "TRIPID": "6161888", "VEHICLE": "2523"}, {"ADHERENCE": "-1", "BLOCKID": "242", "BLOCK_ABBR": "2-4", "DIRECTION": "Westbound", "LATITUDE": "33.7669273", "LONGITUDE": "-84.3141269", "MSGTIME": "4/16/2018 6:58:50 PM", "ROUTE": "2", "STOPID": "904323", "TIMEPOINT": "East Lake Station (South Loop)", "TRIPID": "6149101", "VEHICLE": "1548"}, {"ADHERENCE": "-18", "BLOCKID": "333", "BLOCK_ABBR": "39-2", "DIRECTION": "Southbound", "LATITUDE": "33.8518552", "LONGITUDE": "-84.3189517", "MSGTIME": "4/16/2018 6:58:51 PM", "ROUTE": "39", "STOPID": "906139", "TIMEPOINT": "Buford Hwy & Clairmont Rd", "TRIPID": "6151615", "VEHICLE": "1705"}, {"ADHERENCE": "-2", "BLOCKID": "177", "BLOCK_ABBR": "172-1", "DIRECTION": "Northbound", "LATITUDE": "33.6795765", "LONGITUDE": "-84.4186235", "MSGTIME": "4/16/2018 6:58:54 PM", "ROUTE": "172", "STOPID": "158158", "TIMEPOINT": "Sylvan Rd & Central Ave", "TRIPID": "6173107", "VEHICLE": "2341"}, {"ADHERENCE": "-8", "BLOCKID": "450", "BLOCK_ABBR": "78-4", "DIRECTION": "Eastbound", "LATITUDE": "33.6812019", "LONGITUDE": "-84.4080301", "MSGTIME": "4/16/2018 6:58:59 PM", "ROUTE": "78", "STOPID": "158178", "TIMEPOINT": "Cleveland Ave & Springdale Rd", "TRIPID": "6160186", "VEHICLE": "2320"}, {"ADHERENCE": "0", "BLOCKID": "107", "BLOCK_ABBR": "125-2", "DIRECTION": "Northbound", "LATITUDE": "33.8050084", "LONGITUDE": "-84.2392356", "MSGTIME": "4/16/2018 6:59:04 PM", "ROUTE": "125", "STOPID": "903908", "TIMEPOINT": "Indian Crk Dr & Memorial College", "TRIPID": "6173295", "VEHICLE": "1553"}, {"ADHERENCE": "0", "BLOCKID": "580", "BLOCK_ABBR": "99-1", "DIRECTION": "Southbound", "LATITUDE": "33.7491261", "LONGITUDE": "-84.3859345", "MSGTIME": "4/16/2018 6:59:06 PM", "ROUTE": "99", "STOPID": "103900", "TIMEPOINT": "King Memorial Station", "TRIPID": "6152829", "VEHICLE": "2545"}, {"ADHERENCE": "-1", "BLOCKID": "77", "BLOCK_ABBR": "120-1", "DIRECTION": "Westbound", "LATITUDE": "33.8184773", "LONGITUDE": "-84.2123714", "MSGTIME": "4/16/2018 6:59:12 PM", "ROUTE": "120", "STOPID": "901501", "TIMEPOINT": "Ponce de Leon Ave & Hairston Rd", "TRIPID": "6172625", "VEHICLE": "1616"}, {"ADHERENCE": "-3", "BLOCKID": "527", "BLOCK_ABBR": "856-4", "DIRECTION": "Westbound", "LATITUDE": "33.758526", "LONGITUDE": "-84.4612487", "MSGTIME": "4/16/2018 6:59:13 PM", "ROUTE": "856", "STOPID": "212992", "TIMEPOINT": "Verbena Cr & Sewanee Ave (S end)", "TRIPID": "6148748", "VEHICLE": "2544"}, {"ADHERENCE": "-2", "BLOCKID": "556", "BLOCK_ABBR": "89-12", "DIRECTION": "Southbound", "LATITUDE": "33.5679362", "LONGITUDE": "-84.537212", "MSGTIME": "4/16/2018 6:59:14 PM", "ROUTE": "89", "STOPID": "900069", "TIMEPOINT": "Lancaster Ln & Shannon Pkwy", "TRIPID": "6171594", "VEHICLE": "2311"}, {"ADHERENCE": "-4", "BLOCKID": "239", "BLOCK_ABBR": "2-1", "DIRECTION": "Westbound", "LATITUDE": "33.7737209", "LONGITUDE": "-84.3635514", "MSGTIME": "4/16/2018 6:59:17 PM", "ROUTE": "102", "STOPID": "211524", "TIMEPOINT": "Ponce de Leon Ave & Highland Ave", "TRIPID": "6160938", "VEHICLE": "2565"}, {"ADHERENCE": "0", "BLOCKID": "454", "BLOCK_ABBR": "78-8", "DIRECTION": "Westbound", "LATITUDE": "33.6786334", "LONGITUDE": "-84.4399129", "MSGTIME": "4/16/2018 6:59:17 PM", "ROUTE": "78", "STOPID": "146900", "TIMEPOINT": "East Point Station", "TRIPID": "6169227", "VEHICLE": "2409"}, {"ADHERENCE": "-6", "BLOCKID": "540", "BLOCK_ABBR": "86-6", "DIRECTION": "Eastbound", "LATITUDE": "33.701232", "LONGITUDE": "-84.1701237", "MSGTIME": "4/16/2018 6:59:28 PM", "ROUTE": "86", "STOPID": "210346", "TIMEPOINT": "GRTA Park & Ride", "TRIPID": "6177386", "VEHICLE": "1439"}, {"ADHERENCE": "-4", "BLOCKID": "546", "BLOCK_ABBR": "87-3", "DIRECTION": "Southbound", "LATITUDE": "33.9756931", "LONGITUDE": "-84.3526766", "MSGTIME": "4/16/2018 6:59:40 PM", "ROUTE": "87", "STOPID": "902852", "TIMEPOINT": "Roswell Rd & Dalrymple Rd", "TRIPID": "6156953", "VEHICLE": "1588"}, {"ADHERENCE": "-1", "BLOCKID": "403", "BLOCK_ABBR": "60-2", "DIRECTION": "Southbound", "LATITUDE": "33.7626553", "LONGITUDE": "-84.4699634", "MSGTIME": "4/16/2018 6:59:41 PM", "ROUTE": "60", "STOPID": "903643", "TIMEPOINT": "James Jackson Py & Hightower Rd", "TRIPID": "6151919", "VEHICLE": "1461"}, {"ADHERENCE": "-2", "BLOCKID": "187", "BLOCK_ABBR": "183-1", "DIRECTION": "Eastbound", "LATITUDE": "33.6977329", "LONGITUDE": "-84.4749349", "MSGTIME": "4/16/2018 6:59:43 PM", "ROUTE": "183", "STOPID": "145314", "TIMEPOINT": "Greenbriar Pkwy & Headland Dr", "TRIPID": "6153546", "VEHICLE": "2308"}, {"ADHERENCE": "1", "BLOCKID": "331", "BLOCK_ABBR": "39-1", "DIRECTION": "Northbound", "LATITUDE": "33.8399534", "LONGITUDE": "-84.3318685", "MSGTIME": "4/16/2018 6:59:43 PM", "ROUTE": "39", "STOPID": "902150", "TIMEPOINT": "Buford Hwy & Druid Hills Rd", "TRIPID": "6177501", "VEHICLE": "1715"}, {"ADHERENCE": "0", "BLOCKID": "467", "BLOCK_ABBR": "81-4", "DIRECTION": "Southbound", "LATITUDE": "33.6778834", "LONGITUDE": "-84.4402538", "MSGTIME": "4/16/2018 6:59:49 PM", "ROUTE": "81", "STOPID": "146900", "TIMEPOINT": "East Point Station", "TRIPID": "6165703", "VEHICLE": "2329"}, {"ADHERENCE": "-4", "BLOCKID": "123", "BLOCK_ABBR": "140-1", "DIRECTION": "Southbound", "LATITUDE": "34.0694097", "LONGITUDE": "-84.2605761", "MSGTIME": "4/16/2018 6:59:53 PM", "ROUTE": "140", "STOPID": "901235", "TIMEPOINT": "North Point Pky & Old Milton Pky", "TRIPID": "6157626", "VEHICLE": "1667"}, {"ADHERENCE": "-1", "BLOCKID": "202", "BLOCK_ABBR": "189-4", "DIRECTION": "Northbound", "LATITUDE": "33.5886538", "LONGITUDE": "-84.4761232", "MSGTIME": "4/16/2018 6:59:55 PM", "ROUTE": "189", "STOPID": "184010", "TIMEPOINT": "Carriage Ln & Hillandale Dr", "TRIPID": "6165584", "VEHICLE": "2391"}, {"ADHERENCE": "0", "BLOCKID": "446", "BLOCK_ABBR": "75-7", "DIRECTION": "Northbound", "LATITUDE": "33.7780238", "LONGITUDE": "-84.2694259", "MSGTIME": "4/16/2018 6:59:58 PM", "ROUTE": "75", "STOPID": "900358", "TIMEPOINT": "Lawrenceville Hwy & Idlewood Rd", "TRIPID": "6156643", "VEHICLE": "2556"}, {"ADHERENCE": "2", "BLOCKID": "271", "BLOCK_ABBR": "24-1", "DIRECTION": "Westbound", "LATITUDE": "33.7421337", "LONGITUDE": "-84.2342187", "MSGTIME": "4/16/2018 7:00:02 PM", "ROUTE": "24", "STOPID": "213294", "TIMEPOINT": "Austin Dr & Corey Blvd", "TRIPID": "6149192", "VEHICLE": "1414"}, {"ADHERENCE": "-1", "BLOCKID": "345", "BLOCK_ABBR": "40-3", "DIRECTION": "Northbound", "LATITUDE": "33.7381625", "LONGITUDE": "-84.4130314", "MSGTIME": "4/16/2018 7:00:07 PM", "ROUTE": "40", "STOPID": "114900", "TIMEPOINT": "West End Station", "TRIPID": "6152800", "VEHICLE": "1561"}, {"ADHERENCE": "-6", "BLOCKID": "393", "BLOCK_ABBR": "6-1", "DIRECTION": "Northbound", "LATITUDE": "33.7902897", "LONGITUDE": "-84.3208763", "MSGTIME": "4/16/2018 7:00:08 PM", "ROUTE": "6", "STOPID": "901796", "TIMEPOINT": "N Decatur Rd & Oxford Rd", "TRIPID": "6168312", "VEHICLE": "2574"}, {"ADHERENCE": "0", "BLOCKID": "423", "BLOCK_ABBR": "73-11", "DIRECTION": "Southbound", "LATITUDE": "33.7689092", "LONGITUDE": "-84.5221656", "MSGTIME": "4/16/2018 7:00:08 PM", "ROUTE": "73", "STOPID": "905269", "TIMEPOINT": "Fulton Ind Blvd & MLK Jr Dr", "TRIPID": "6172115", "VEHICLE": "2526"}, {"ADHERENCE": "-2", "BLOCKID": "466", "BLOCK_ABBR": "81-3", "DIRECTION": "Southbound", "LATITUDE": "33.6970288", "LONGITUDE": "-84.373958", "MSGTIME": "4/16/2018 7:00:08 PM", "ROUTE": "81", "STOPID": "139046", "TIMEPOINT": "Lakewood Ave & Jonesboro Rd", "TRIPID": "6174987", "VEHICLE": "2314"}, {"ADHERENCE": "-5", "BLOCKID": "433", "BLOCK_ABBR": "74-1", "DIRECTION": "Eastbound", "LATITUDE": "33.7118066", "LONGITUDE": "-84.2898878", "MSGTIME": "4/16/2018 7:00:13 PM", "ROUTE": "74", "STOPID": "129292", "TIMEPOINT": "Whites Mill Rd & Tregoney Dr", "TRIPID": "6168761", "VEHICLE": "1630"}, {"ADHERENCE": "-5", "BLOCKID": "294", "BLOCK_ABBR": "3-1", "DIRECTION": "Westbound", "LATITUDE": "33.7350267", "LONGITUDE": "-84.4134468", "MSGTIME": "4/16/2018 7:00:21 PM", "ROUTE": "3", "STOPID": "114900", "TIMEPOINT": "West End Station", "TRIPID": "6148757", "VEHICLE": "1441"}, {"ADHERENCE": "-5", "BLOCKID": "438", "BLOCK_ABBR": "74-6", "DIRECTION": "Eastbound", "LATITUDE": "33.7401604", "LONGITUDE": "-84.3491277", "MSGTIME": "4/16/2018 7:00:23 PM", "ROUTE": "74", "STOPID": "117044", "TIMEPOINT": "Glenwood Ave & Moreland Ave", "TRIPID": "6148798", "VEHICLE": "1413"}, {"ADHERENCE": "0", "BLOCKID": "97", "BLOCK_ABBR": "121-9", "DIRECTION": "Southbound", "LATITUDE": "33.8264588", "LONGITUDE": "-84.1959687", "MSGTIME": "4/16/2018 7:00:23 PM", "ROUTE": "121", "STOPID": "902109", "TIMEPOINT": "Ponce de Leon Ave & Hairston Rd", "TRIPID": "6157582", "VEHICLE": "2587"}, {"ADHERENCE": "8", "BLOCKID": "343", "BLOCK_ABBR": "40-1", "DIRECTION": "Southbound", "LATITUDE": "33.8105256", "LONGITUDE": "-84.4776679", "MSGTIME": "4/16/2018 7:00:23 PM", "ROUTE": "40", "STOPID": "210300", "TIMEPOINT": "Bolton Rd & Parrot Ave", "TRIPID": "6172235", "VEHICLE": "1673"}, {"ADHERENCE": "0", "BLOCKID": "175", "BLOCK_ABBR": "162-1", "DIRECTION": "Westbound", "LATITUDE": "33.7176919", "LONGITUDE": "-84.4272792", "MSGTIME": "4/16/2018 7:00:25 PM", "ROUTE": "162", "STOPID": "123900", "TIMEPOINT": "Oakland City Station", "TRIPID": "6153526", "VEHICLE": "2301"}, {"ADHERENCE": "0", "BLOCKID": "335", "BLOCK_ABBR": "39-4", "DIRECTION": "Northbound", "LATITUDE": "33.9026638", "LONGITUDE": "-84.280362", "MSGTIME": "4/16/2018 7:00:27 PM", "ROUTE": "39", "STOPID": "905508", "TIMEPOINT": "Doraville Station", "TRIPID": "6168869", "VEHICLE": "1714"}, {"ADHERENCE": "0", "BLOCKID": "521", "BLOCK_ABBR": "850-2", "DIRECTION": "Eastbound", "LATITUDE": "33.7542741", "LONGITUDE": "-84.4694861", "MSGTIME": "4/16/2018 7:00:28 PM", "ROUTE": "850", "STOPID": "903320", "TIMEPOINT": "Hamilton E Holmes Station", "TRIPID": "6146180", "VEHICLE": "2531"}, {"ADHERENCE": "2", "BLOCKID": "547", "BLOCK_ABBR": "87-4", "DIRECTION": "Northbound", "LATITUDE": "33.9442002", "LONGITUDE": "-84.3573642", "MSGTIME": "4/16/2018 7:00:29 PM", "ROUTE": "87", "STOPID": "902725", "TIMEPOINT": "North Springs Station", "TRIPID": "6169517", "VEHICLE": "1671"}, {"ADHERENCE": "0", "BLOCKID": "372", "BLOCK_ABBR": "50-1", "DIRECTION": "Eastbound", "LATITUDE": "33.7763479", "LONGITUDE": "-84.4739323", "MSGTIME": "4/16/2018 7:00:32 PM", "ROUTE": "50", "STOPID": "905740", "TIMEPOINT": "HE Holmes & DL Hollowell Pkwy", "TRIPID": "6178328", "VEHICLE": "1586"}, {"ADHERENCE": "-4", "BLOCKID": "121", "BLOCK_ABBR": "14-4", "DIRECTION": "Eastbound", "LATITUDE": "33.7858391", "LONGITUDE": "-84.4096895", "MSGTIME": "4/16/2018 7:00:34 PM", "ROUTE": "14", "STOPID": "213387", "TIMEPOINT": "14th St & Howell Mill Rd", "TRIPID": "6178144", "VEHICLE": "1675"}, {"ADHERENCE": "-8", "BLOCKID": "477", "BLOCK_ABBR": "82-3", "DIRECTION": "Eastbound", "LATITUDE": "33.6514076", "LONGITUDE": "-84.4890452", "MSGTIME": "4/16/2018 7:00:35 PM", "ROUTE": "82", "STOPID": "165056", "TIMEPOINT": "Washington Rd & Lakemont Dr", "TRIPID": "6142030", "VEHICLE": "2392"}, {"ADHERENCE": "0", "BLOCKID": "260", "BLOCK_ABBR": "21-4", "DIRECTION": "Eastbound", "LATITUDE": "33.7490683", "LONGITUDE": "-84.3868484", "MSGTIME": "4/16/2018 7:00:37 PM", "ROUTE": "21", "STOPID": "210431", "TIMEPOINT": "Georgia State Station (East)", "TRIPID": "6171206", "VEHICLE": "1617"}, {"ADHERENCE": "-1", "BLOCKID": "449", "BLOCK_ABBR": "78-3", "DIRECTION": "Eastbound", "LATITUDE": "33.6760723", "LONGITUDE": "-84.4404847", "MSGTIME": "4/16/2018 7:00:38 PM", "ROUTE": "78", "STOPID": "146900", "TIMEPOINT": "East Point Station", "TRIPID": "6177189", "VEHICLE": "2328"}, {"ADHERENCE": "0", "BLOCKID": "330", "BLOCK_ABBR": "36-3", "DIRECTION": "Eastbound", "LATITUDE": "33.7364505", "LONGITUDE": "-84.4799752", "MSGTIME": "4/16/2018 7:00:40 PM", "ROUTE": "36", "STOPID": "903499", "TIMEPOINT": "N Decatur Rd & Clairmont Rd", "TRIPID": "6151605", "VEHICLE": "2595"}, {"ADHERENCE": "-5", "BLOCKID": "319", "BLOCK_ABBR": "32-7", "DIRECTION": "Northbound", "LATITUDE": "33.6889323", "LONGITUDE": "-84.3132187", "MSGTIME": "4/16/2018 7:00:41 PM", "ROUTE": "32", "STOPID": "152022", "TIMEPOINT": "Bouldercrest Rd & Clifton Church", "TRIPID": "6149218", "VEHICLE": "2309"}, {"ADHERENCE": "-1", "BLOCKID": "375", "BLOCK_ABBR": "51-1", "DIRECTION": "Westbound", "LATITUDE": "33.7683316", "LONGITUDE": "-84.396116", "MSGTIME": "4/16/2018 7:00:42 PM", "ROUTE": "51", "STOPID": "211576", "TIMEPOINT": "Luckie St & Merritts Ave", "TRIPID": "6149840", "VEHICLE": "1577"}, {"ADHERENCE": "-2", "BLOCKID": "39", "BLOCK_ABBR": "115-4", "DIRECTION": "Eastbound", "LATITUDE": "33.7597619", "LONGITUDE": "-84.1771968", "MSGTIME": "4/16/2018 7:00:43 PM", "ROUTE": "115", "STOPID": "903453", "TIMEPOINT": "Redan Rd & Martin Rd", "TRIPID": "6160362", "VEHICLE": "1557"}, {"ADHERENCE": "-1", "BLOCKID": "383", "BLOCK_ABBR": "55-1", "DIRECTION": "Southbound", "LATITUDE": "33.7529043", "LONGITUDE": "-84.3932785", "MSGTIME": "4/16/2018 7:00:43 PM", "ROUTE": "55", "STOPID": "102274", "TIMEPOINT": "Alabama St & Forsyth St", "TRIPID": "6164920", "VEHICLE": "1843"}, {"ADHERENCE": "0", "BLOCKID": "41", "BLOCK_ABBR": "115-6", "DIRECTION": "Eastbound", "LATITUDE": "33.771735", "LONGITUDE": "-84.2517747", "MSGTIME": "4/16/2018 7:00:45 PM", "ROUTE": "115", "STOPID": "900686", "TIMEPOINT": "Kensington Station", "TRIPID": "6152889", "VEHICLE": "1405"}, {"ADHERENCE": "-2", "BLOCKID": "456", "BLOCK_ABBR": "79-2", "DIRECTION": "Southbound", "LATITUDE": "33.6991785", "LONGITUDE": "-84.4183519", "MSGTIME": "4/16/2018 7:00:47 PM", "ROUTE": "79", "STOPID": "136124", "TIMEPOINT": "Sylvan Rd & Estes Dr", "TRIPID": "6142016", "VEHICLE": "2334"}, {"ADHERENCE": "4", "BLOCKID": "539", "BLOCK_ABBR": "86-5", "DIRECTION": "Eastbound", "LATITUDE": "33.7057698", "LONGITUDE": "-84.1658907", "MSGTIME": "4/16/2018 7:00:48 PM", "ROUTE": "86", "STOPID": "131096", "TIMEPOINT": "Snapfinger Wds & Wesley Chapel", "TRIPID": "6145771", "VEHICLE": "2569"}, {"ADHERENCE": "-1", "BLOCKID": "71", "BLOCK_ABBR": "12-4", "DIRECTION": "Northbound", "LATITUDE": "33.7811011", "LONGITUDE": "-84.3878419", "MSGTIME": "4/16/2018 7:00:48 PM", "ROUTE": "12", "STOPID": "904800", "TIMEPOINT": "Midtown Station", "TRIPID": "6158927", "VEHICLE": "2504"}, {"ADHERENCE": "-2", "BLOCKID": "169", "BLOCK_ABBR": "16-2", "DIRECTION": "Northbound", "LATITUDE": "33.8054168", "LONGITUDE": "-84.3366847", "MSGTIME": "4/16/2018 7:00:48 PM", "ROUTE": "16", "STOPID": "901834", "TIMEPOINT": "Johnson Rd & Briarcliff Rd", "TRIPID": "6155714", "VEHICLE": "1644"}, {"ADHERENCE": "-5", "BLOCKID": "328", "BLOCK_ABBR": "36-1", "DIRECTION": "Westbound", "LATITUDE": "33.7814155", "LONGITUDE": "-84.3727784", "MSGTIME": "4/16/2018 7:00:51 PM", "ROUTE": "36", "STOPID": "906327", "TIMEPOINT": "10th St & Charles Allen Dr", "TRIPID": "6175261", "VEHICLE": "1634"}, {"ADHERENCE": "-3", "BLOCKID": "209", "BLOCK_ABBR": "19-6", "DIRECTION": "Southbound", "LATITUDE": "33.7901991", "LONGITUDE": "-84.3065673", "MSGTIME": "4/16/2018 7:00:55 PM", "ROUTE": "19", "STOPID": "903960", "TIMEPOINT": "Clairmont Rd & North Decatur Rd", "TRIPID": "6170597", "VEHICLE": "1518"}, {"ADHERENCE": "-2", "BLOCKID": "498", "BLOCK_ABBR": "84-15", "DIRECTION": "Westbound", "LATITUDE": "33.6660873", "LONGITUDE": "-84.4660592", "MSGTIME": "4/16/2018 7:00:55 PM", "ROUTE": "84", "STOPID": "166144", "TIMEPOINT": "Washington Rd & Stone Rd", "TRIPID": "6158884", "VEHICLE": "2368"}, {"ADHERENCE": "-1", "BLOCKID": "351", "BLOCK_ABBR": "42-3", "DIRECTION": "Northbound", "LATITUDE": "33.7015316", "LONGITUDE": "-84.4260811", "MSGTIME": "4/16/2018 7:00:59 PM", "ROUTE": "42", "STOPID": "136901", "TIMEPOINT": "Lakewood Station", "TRIPID": "6168887", "VEHICLE": "2378"}, {"ADHERENCE": "-1", "BLOCKID": "329", "BLOCK_ABBR": "36-2", "DIRECTION": "Westbound", "LATITUDE": "33.7745995", "LONGITUDE": "-84.2972587", "MSGTIME": "4/16/2018 7:01:01 PM", "ROUTE": "36", "STOPID": "212946", "TIMEPOINT": "Decatur Station", "TRIPID": "6154929", "VEHICLE": "1604"}, {"ADHERENCE": "-5", "BLOCKID": "439", "BLOCK_ABBR": "74-7", "DIRECTION": "Westbound", "LATITUDE": "33.7107371", "LONGITUDE": "-84.2925822", "MSGTIME": "4/16/2018 7:01:01 PM", "ROUTE": "74", "STOPID": "129294", "TIMEPOINT": "Whites Mill Rd & Tregoney Dr", "TRIPID": "6155297", "VEHICLE": "1632"}, {"ADHERENCE": "-2", "BLOCKID": "359", "BLOCK_ABBR": "49-4", "DIRECTION": "Northbound", "LATITUDE": "33.7034837", "LONGITUDE": "-84.3532834", "MSGTIME": "4/16/2018 7:01:03 PM", "ROUTE": "49", "STOPID": "140156", "TIMEPOINT": "Kipling St & Henry Thomas Dr (E)", "TRIPID": "6164911", "VEHICLE": "2331"}, {"ADHERENCE": "2", "BLOCKID": "554", "BLOCK_ABBR": "89-10", "DIRECTION": "Southbound", "LATITUDE": "33.6156963", "LONGITUDE": "-84.4728511", "MSGTIME": "4/16/2018 7:01:03 PM", "ROUTE": "89", "STOPID": "176090", "TIMEPOINT": "Old Natl Hwy & Godby Rd", "TRIPID": "6147662", "VEHICLE": "2396"}, {"ADHERENCE": "-10", "BLOCKID": "299", "BLOCK_ABBR": "3-6", "DIRECTION": "Eastbound", "LATITUDE": "33.759378", "LONGITUDE": "-84.3702429", "MSGTIME": "4/16/2018 7:01:04 PM", "ROUTE": "3", "STOPID": "901227", "TIMEPOINT": "Helene Mills Senior Center", "TRIPID": "6155657", "VEHICLE": "2512"}, {"ADHERENCE": "1", "BLOCKID": "282", "BLOCK_ABBR": "26-4", "DIRECTION": "Northbound", "LATITUDE": "33.7910133", "LONGITUDE": "-84.4418976", "MSGTIME": "4/16/2018 7:01:08 PM", "ROUTE": "26", "STOPID": "902136", "TIMEPOINT": "Perry Blvd @ MARTA", "TRIPID": "6155990", "VEHICLE": "2549"}, {"ADHERENCE": "0", "BLOCKID": "473", "BLOCK_ABBR": "813-4", "DIRECTION": "Westbound", "LATITUDE": "33.7529884", "LONGITUDE": "-84.4443166", "MSGTIME": "4/16/2018 7:01:09 PM", "ROUTE": "813", "STOPID": "900232", "TIMEPOINT": "West Lake Station (East Loop)", "TRIPID": "6177467", "VEHICLE": "2313"}, {"ADHERENCE": "-1", "BLOCKID": "193", "BLOCK_ABBR": "186-4", "DIRECTION": "Eastbound", "LATITUDE": "33.7539632", "LONGITUDE": "-84.3925571", "MSGTIME": "4/16/2018 7:01:10 PM", "ROUTE": "186", "STOPID": "213360", "TIMEPOINT": "Alabama St & Broad St (5 Pts)", "TRIPID": "6177667", "VEHICLE": "1609"}, {"ADHERENCE": "-1", "BLOCKID": "174", "BLOCK_ABBR": "16-7", "DIRECTION": "Northbound", "LATITUDE": "33.7535327", "LONGITUDE": "-84.3904133", "MSGTIME": "4/16/2018 7:01:10 PM", "ROUTE": "16", "STOPID": "102258", "TIMEPOINT": "Alabama St & Broad St (5 Pts)", "TRIPID": "6168570", "VEHICLE": "1545"}, {"ADHERENCE": "2", "BLOCKID": "427", "BLOCK_ABBR": "73-4", "DIRECTION": "Southbound", "LATITUDE": "33.7329956", "LONGITUDE": "-84.5682864", "MSGTIME": "4/16/2018 7:01:10 PM", "ROUTE": "73", "STOPID": "901381", "TIMEPOINT": "Fulton Ind Blvd & Cascade Rd", "TRIPID": "6156626", "VEHICLE": "1470"}, {"ADHERENCE": "-6", "BLOCKID": "310", "BLOCK_ABBR": "30-7", "DIRECTION": "Westbound", "LATITUDE": "33.8248115", "LONGITUDE": "-84.2927149", "MSGTIME": "4/16/2018 7:01:11 PM", "ROUTE": "30", "STOPID": "902076", "TIMEPOINT": "LaVista Rd & Oak Grove Rd", "TRIPID": "6164604", "VEHICLE": "1532"}, {"ADHERENCE": "-9", "BLOCKID": "42", "BLOCK_ABBR": "115-7", "DIRECTION": "Westbound", "LATITUDE": "33.7617577", "LONGITUDE": "-84.196096", "MSGTIME": "4/16/2018 7:01:12 PM", "ROUTE": "115", "STOPID": "900939", "TIMEPOINT": "Redan Rd & S Hairston Rd", "TRIPID": "6142273", "VEHICLE": "1623"}, {"ADHERENCE": "-1", "BLOCKID": "342", "BLOCK_ABBR": "4-2", "DIRECTION": "Southbound", "LATITUDE": "33.7576546", "LONGITUDE": "-84.3518602", "MSGTIME": "4/16/2018 7:01:16 PM", "ROUTE": "4", "STOPID": "901066", "TIMEPOINT": "Inman Park Station (South Loop)", "TRIPID": "6151252", "VEHICLE": "1404"}, {"ADHERENCE": "0", "BLOCKID": "465", "BLOCK_ABBR": "81-2", "DIRECTION": "Northbound", "LATITUDE": "33.7363915", "LONGITUDE": "-84.4135322", "MSGTIME": "4/16/2018 7:01:17 PM", "ROUTE": "81", "STOPID": "114900", "TIMEPOINT": "West End Station", "TRIPID": "6160851", "VEHICLE": "2312"}, {"ADHERENCE": "3", "BLOCKID": "81", "BLOCK_ABBR": "120-2", "DIRECTION": "Eastbound", "LATITUDE": "33.810878", "LONGITUDE": "-84.182509", "MSGTIME": "4/16/2018 7:01:18 PM", "ROUTE": "120", "STOPID": "211482", "TIMEPOINT": "Memorial Drive Park & Ride", "TRIPID": "0", "VEHICLE": "1517"}, {"ADHERENCE": "-1", "BLOCKID": "283", "BLOCK_ABBR": "27-1", "DIRECTION": "Southbound", "LATITUDE": "33.8235024", "LONGITUDE": "-84.3674695", "MSGTIME": "4/16/2018 7:01:20 PM", "ROUTE": "27", "STOPID": "902145", "TIMEPOINT": "Lindbergh Ctr Station (N Loop)", "TRIPID": "6155993", "VEHICLE": "1661"}, {"ADHERENCE": "0", "BLOCKID": "440", "BLOCK_ABBR": "75-1", "DIRECTION": "Southbound", "LATITUDE": "33.7756609", "LONGITUDE": "-84.2818757", "MSGTIME": "4/16/2018 7:01:20 PM", "ROUTE": "75", "STOPID": "904264", "TIMEPOINT": "Avondale Station (North Loop)", "TRIPID": "6156644", "VEHICLE": "1432"}, {"ADHERENCE": "-1", "BLOCKID": "280", "BLOCK_ABBR": "26-2", "DIRECTION": "Northbound", "LATITUDE": "33.7521685", "LONGITUDE": "-84.3920744", "MSGTIME": "4/16/2018 7:01:21 PM", "ROUTE": "26", "STOPID": "102258", "TIMEPOINT": "Alabama St & Broad St (5 Pts)", "TRIPID": "6149205", "VEHICLE": "2525"}, {"ADHERENCE": "-1", "BLOCKID": "241", "BLOCK_ABBR": "2-3", "DIRECTION": "Eastbound", "LATITUDE": "33.7723827", "LONGITUDE": "-84.3838126", "MSGTIME": "4/16/2018 7:01:22 PM", "ROUTE": "102", "STOPID": "907473", "TIMEPOINT": "North Ave Station", "TRIPID": "6149328", "VEHICLE": "1640"}, {"ADHERENCE": "-6", "BLOCKID": "61", "BLOCK_ABBR": "119-1", "DIRECTION": "Westbound", "LATITUDE": "33.7670259", "LONGITUDE": "-84.2277873", "MSGTIME": "4/16/2018 7:01:23 PM", "ROUTE": "119", "STOPID": "903391", "TIMEPOINT": "Indian Creek Station (East Loop)", "TRIPID": "6157328", "VEHICLE": "1521"}, {"ADHERENCE": "-2", "BLOCKID": "82", "BLOCK_ABBR": "120-3", "DIRECTION": "Westbound", "LATITUDE": "33.7934238", "LONGITUDE": "-84.2641472", "MSGTIME": "4/16/2018 7:01:23 PM", "ROUTE": "120", "STOPID": "904010", "TIMEPOINT": "Ponce de Leon Ave & Decatur Rd", "TRIPID": "6157334", "VEHICLE": "2591"}, {"ADHERENCE": "-3", "BLOCKID": "25", "BLOCK_ABBR": "110-4", "DIRECTION": "Southbound", "LATITUDE": "33.8455165", "LONGITUDE": "-84.3687057", "MSGTIME": "4/16/2018 7:01:35 PM", "ROUTE": "110", "STOPID": "905889", "TIMEPOINT": "Buckhead Station", "TRIPID": "6152818", "VEHICLE": "1563"}, {"ADHERENCE": "-2", "BLOCKID": "455", "BLOCK_ABBR": "79-1", "DIRECTION": "Northbound", "LATITUDE": "33.6763805", "LONGITUDE": "-84.4404899", "MSGTIME": "4/16/2018 7:01:38 PM", "ROUTE": "79", "STOPID": "146900", "TIMEPOINT": "East Point Station", "TRIPID": "6160194", "VEHICLE": "2335"}, {"ADHERENCE": "-4", "BLOCKID": "365", "BLOCK_ABBR": "5-2", "DIRECTION": "Southbound", "LATITUDE": "33.854654", "LONGITUDE": "-84.3827105", "MSGTIME": "4/16/2018 7:01:39 PM", "ROUTE": "5", "STOPID": "905526", "TIMEPOINT": "Piedmont Rd & Peachtree Rd", "TRIPID": "6168295", "VEHICLE": "2538"}, {"ADHERENCE": "-1", "BLOCKID": "404", "BLOCK_ABBR": "60-3", "DIRECTION": "Northbound", "LATITUDE": "33.752958", "LONGITUDE": "-84.4687447", "MSGTIME": "4/16/2018 7:01:40 PM", "ROUTE": "60", "STOPID": "903320", "TIMEPOINT": "Hamilton E Holmes Station", "TRIPID": "6151923", "VEHICLE": "1578"}, {"ADHERENCE": "-2", "BLOCKID": "112", "BLOCK_ABBR": "126-3", "DIRECTION": "Eastbound", "LATITUDE": "33.8863134", "LONGITUDE": "-84.3064292", "MSGTIME": "4/16/2018 7:01:45 PM", "ROUTE": "126", "STOPID": "905514", "TIMEPOINT": "Chamblee Station (East Loop)", "TRIPID": "6149443", "VEHICLE": "2558"}, {"ADHERENCE": "-2", "BLOCKID": "257", "BLOCK_ABBR": "21-1", "DIRECTION": "Eastbound", "LATITUDE": "33.7723893", "LONGITUDE": "-84.2523265", "MSGTIME": "4/16/2018 7:01:45 PM", "ROUTE": "21", "STOPID": "900686", "TIMEPOINT": "Kensington Station", "TRIPID": "6141956", "VEHICLE": "1433"}, {"ADHERENCE": "-2", "BLOCKID": "525", "BLOCK_ABBR": "856-2", "DIRECTION": "Westbound", "LATITUDE": "33.7530056", "LONGITUDE": "-84.468708", "MSGTIME": "4/16/2018 7:01:48 PM", "ROUTE": "856", "STOPID": "903320", "TIMEPOINT": "Hamilton E Holmes Station", "TRIPID": "6156320", "VEHICLE": "1680"}, {"ADHERENCE": "-2", "BLOCKID": "161", "BLOCK_ABBR": "15-9", "DIRECTION": "Southbound", "LATITUDE": "33.7746067", "LONGITUDE": "-84.2986925", "MSGTIME": "4/16/2018 7:01:49 PM", "ROUTE": "15", "STOPID": "904262", "TIMEPOINT": "Decatur Station", "TRIPID": "6145556", "VEHICLE": "1555"}, {"ADHERENCE": "1", "BLOCKID": "379", "BLOCK_ABBR": "51-5", "DIRECTION": "Northbound", "LATITUDE": "33.7555037", "LONGITUDE": "-84.4999824", "MSGTIME": "4/16/2018 7:01:53 PM", "ROUTE": "51", "STOPID": "903840", "TIMEPOINT": "MLK Jr Dr & Brownlee Rd", "TRIPID": "6162110", "VEHICLE": "1456"}, {"ADHERENCE": "0", "BLOCKID": "184", "BLOCK_ABBR": "180-2", "DIRECTION": "Northbound", "LATITUDE": "33.6002184", "LONGITUDE": "-84.5480438", "MSGTIME": "4/16/2018 7:01:55 PM", "ROUTE": "180", "STOPID": "182025", "TIMEPOINT": "Camp Dr & Stonewall Tell Rd", "TRIPID": "6157931", "VEHICLE": "2406"}, {"ADHERENCE": "-1", "BLOCKID": "158", "BLOCK_ABBR": "15-6", "DIRECTION": "Southbound", "LATITUDE": "33.6458751", "LONGITUDE": "-84.2817336", "MSGTIME": "4/16/2018 7:01:57 PM", "ROUTE": "15", "STOPID": "212185", "TIMEPOINT": "Bouldercrest Rd & Linecrest Rd", "TRIPID": "6170373", "VEHICLE": "2559"}, {"ADHERENCE": "-2", "BLOCKID": "201", "BLOCK_ABBR": "189-3", "DIRECTION": "Southbound", "LATITUDE": "33.588844", "LONGITUDE": "-84.4691446", "MSGTIME": "4/16/2018 7:01:58 PM", "ROUTE": "189", "STOPID": "184036", "TIMEPOINT": "Flat Shoals Rd & Old Natl Hwy", "TRIPID": "6146033", "VEHICLE": "2389"}, {"ADHERENCE": "-2", "BLOCKID": "296", "BLOCK_ABBR": "3-3", "DIRECTION": "Eastbound", "LATITUDE": "33.7530382", "LONGITUDE": "-84.4687424", "MSGTIME": "4/16/2018 7:02:00 PM", "ROUTE": "3", "STOPID": "903320", "TIMEPOINT": "Hamilton E Holmes Station", "TRIPID": "6156357", "VEHICLE": "1471"}, {"ADHERENCE": "-1", "BLOCKID": "155", "BLOCK_ABBR": "15-3", "DIRECTION": "Northbound", "LATITUDE": "33.6983527", "LONGITUDE": "-84.2709943", "MSGTIME": "4/16/2018 7:02:01 PM", "ROUTE": "15", "STOPID": "153016", "TIMEPOINT": "Panthersville Rd & Clifton Sp Rd", "TRIPID": "6164312", "VEHICLE": "1635"}, {"ADHERENCE": "0", "BLOCKID": "412", "BLOCK_ABBR": "71-11", "DIRECTION": "Eastbound", "LATITUDE": "33.7363589", "LONGITUDE": "-84.4134216", "MSGTIME": "4/16/2018 7:02:03 PM", "ROUTE": "71", "STOPID": "114900", "TIMEPOINT": "West End Station", "TRIPID": "6146153", "VEHICLE": "1567"}, {"ADHERENCE": "-3", "BLOCKID": "272", "BLOCK_ABBR": "24-2", "DIRECTION": "Eastbound", "LATITUDE": "33.721566", "LONGITUDE": "-84.2623661", "MSGTIME": "4/16/2018 7:02:04 PM", "ROUTE": "24", "STOPID": "212868", "TIMEPOINT": "Green Forrest Dr & Glendale Dr", "TRIPID": "6174796", "VEHICLE": "1643"}, {"ADHERENCE": "-3", "BLOCKID": "28", "BLOCK_ABBR": "115-1", "DIRECTION": "Westbound", "LATITUDE": "33.7228239", "LONGITUDE": "-84.1656391", "MSGTIME": "4/16/2018 7:02:05 PM", "ROUTE": "115", "STOPID": "134005", "TIMEPOINT": "Covington Hwy & Panola Rd", "TRIPID": "6174603", "VEHICLE": "1544"}, {"ADHERENCE": "-5", "BLOCKID": "15", "BLOCK_ABBR": "107-4", "DIRECTION": "Eastbound", "LATITUDE": "33.737864", "LONGITUDE": "-84.2515771", "MSGTIME": "4/16/2018 7:02:06 PM", "ROUTE": "107", "STOPID": "107140", "TIMEPOINT": "Columbia Dr & Glenwood Rd", "TRIPID": "6157269", "VEHICLE": "1527"}, {"ADHERENCE": "2", "BLOCKID": "523", "BLOCK_ABBR": "850-4", "DIRECTION": "Southbound", "LATITUDE": "33.7542821", "LONGITUDE": "-84.4685184", "MSGTIME": "4/16/2018 7:02:06 PM", "ROUTE": "850", "STOPID": "903320", "TIMEPOINT": "Hamilton E Holmes Station", "TRIPID": "6146183", "VEHICLE": "1463"}, {"ADHERENCE": "-2", "BLOCKID": "89", "BLOCK_ABBR": "121-1", "DIRECTION": "Northbound", "LATITUDE": "33.7718158", "LONGITUDE": "-84.2511542", "MSGTIME": "4/16/2018 7:02:07 PM", "ROUTE": "121", "STOPID": "900686", "TIMEPOINT": "Kensington Station", "TRIPID": "6157592", "VEHICLE": "1505"}, {"ADHERENCE": "0", "BLOCKID": "569", "BLOCK_ABBR": "9-5", "DIRECTION": "Northbound", "LATITUDE": "33.7197574", "LONGITUDE": "-84.3302665", "MSGTIME": "4/16/2018 7:02:07 PM", "ROUTE": "9", "STOPID": "128048", "TIMEPOINT": "Bouldercrest Dr & Brannen Rd", "TRIPID": "6175582", "VEHICLE": "2589"}, {"ADHERENCE": "-3", "BLOCKID": "160", "BLOCK_ABBR": "15-8", "DIRECTION": "Southbound", "LATITUDE": "33.7381138", "LONGITUDE": "-84.2878207", "MSGTIME": "4/16/2018 7:02:08 PM", "ROUTE": "15", "STOPID": "106094", "TIMEPOINT": "Candler Rd & Glenwood Rd", "TRIPID": "6160035", "VEHICLE": "2551"}, {"ADHERENCE": "-1", "BLOCKID": "127", "BLOCK_ABBR": "141-1", "DIRECTION": "Northbound", "LATITUDE": "34.0388726", "LONGITUDE": "-84.3108582", "MSGTIME": "4/16/2018 7:02:10 PM", "ROUTE": "141", "STOPID": "903177", "TIMEPOINT": "Mansell Park & Ride", "TRIPID": "6165274", "VEHICLE": "1565"}, {"ADHERENCE": "-2", "BLOCKID": "204", "BLOCK_ABBR": "19-1", "DIRECTION": "Northbound", "LATITUDE": "33.7745992", "LONGITUDE": "-84.2980703", "MSGTIME": "4/16/2018 7:02:10 PM", "ROUTE": "19", "STOPID": "904262", "TIMEPOINT": "Decatur Station", "TRIPID": "6170375", "VEHICLE": "1515"}, {"ADHERENCE": "-1", "BLOCKID": "11", "BLOCK_ABBR": "104-2", "DIRECTION": "Southbound", "LATITUDE": "33.9263683", "LONGITUDE": "-84.2692746", "MSGTIME": "4/16/2018 7:02:10 PM", "ROUTE": "104", "STOPID": "905376", "TIMEPOINT": "Winters Chapel Rd & Oakcliff Rd", "TRIPID": "6145736", "VEHICLE": "2567"}, {"ADHERENCE": "12", "BLOCKID": "515", "BLOCK_ABBR": "85-5", "DIRECTION": "Northbound", "LATITUDE": "34.0678356", "LONGITUDE": "-84.2622203", "MSGTIME": "4/16/2018 7:02:11 PM", "ROUTE": "185", "STOPID": "212061", "TIMEPOINT": "North Point Pky & Old Milton Pky", "TRIPID": "6161891", "VEHICLE": "1574"}, {"ADHERENCE": "1", "BLOCKID": "122", "BLOCK_ABBR": "14-5", "DIRECTION": "Westbound", "LATITUDE": "33.8025137", "LONGITUDE": "-84.4310676", "MSGTIME": "4/16/2018 7:02:12 PM", "ROUTE": "14", "STOPID": "901452", "TIMEPOINT": "Chattahoochee Av & Southland Cir", "TRIPID": "6158605", "VEHICLE": "1479"}, {"ADHERENCE": "-2", "BLOCKID": "118", "BLOCK_ABBR": "14-1", "DIRECTION": "Westbound", "LATITUDE": "33.7917232", "LONGITUDE": "-84.3878665", "MSGTIME": "4/16/2018 7:02:12 PM", "ROUTE": "37", "STOPID": "901789", "TIMEPOINT": "Arts Center Station", "TRIPID": "6141454", "VEHICLE": "1575"}, {"ADHERENCE": "-8", "BLOCKID": "461", "BLOCK_ABBR": "8-4", "DIRECTION": "Northbound", "LATITUDE": "33.8601573", "LONGITUDE": "-84.3391342", "MSGTIME": "4/16/2018 7:02:13 PM", "ROUTE": "8", "STOPID": "905697", "TIMEPOINT": "Brookhaven Station", "TRIPID": "6151276", "VEHICLE": "1558"}, {"ADHERENCE": "0", "BLOCKID": "152", "BLOCK_ABBR": "148-2", "DIRECTION": "Eastbound", "LATITUDE": "33.9077477", "LONGITUDE": "-84.4380869", "MSGTIME": "4/16/2018 7:02:14 PM", "ROUTE": "148", "STOPID": "903137", "TIMEPOINT": "RiverEdge Center", "TRIPID": "6161587", "VEHICLE": "2520"}, {"ADHERENCE": "2", "BLOCKID": "414", "BLOCK_ABBR": "71-3", "DIRECTION": "Westbound", "LATITUDE": "33.7340531", "LONGITUDE": "-84.5325442", "MSGTIME": "4/16/2018 7:02:16 PM", "ROUTE": "71", "STOPID": "900861", "TIMEPOINT": "Country Squire Apartments", "TRIPID": "6169185", "VEHICLE": "1686"}, {"ADHERENCE": "-2", "BLOCKID": "336", "BLOCK_ABBR": "39-5", "DIRECTION": "Northbound", "LATITUDE": "33.8501615", "LONGITUDE": "-84.320536", "MSGTIME": "4/16/2018 7:02:23 PM", "ROUTE": "39", "STOPID": "906138", "TIMEPOINT": "Buford Hwy & Clairmont Rd", "TRIPID": "6168877", "VEHICLE": "1520"}]